Workbook
Name AccountList: Setup!$AA$2:$AA$3
Name CategoryList: Setup!$A$10:$A$28
Name Children: Setup!$P$2:$P$3
Name ColumnTitle1: #REF!
Name Debt: Setup!$V$2:$V$4
Name Entertainment: Setup!$R$2:$R$4
Name Food: Setup!$M$2:$M$4
Name Giving: Setup!$T$2:$T$3
Name Housing: Setup!$J$2:$J$7
Name Insurance: Setup!$N$2:$N$3
Name Legal: Setup!$Y$2
Name Medical: Setup!$O$2:$O$4
Name Miscellaneous: Setup!$Z$2:$Z$5
Name Personal_Care: Setup!$Q$2:$Q$4
Name Pets: Setup!$U$2
Name Savings: Setup!$W$2:$W$5
Name Subscriptions: Setup!$S$2:$S$5
Name Taxes: Setup!$X$2
Name Utilities: Setup!$K$2:$K$6
Name Vehicle: Setup!$L$2:$L$6

Sheet Instructions
A1: HOW TO USE THIS HOUSEHOLD BUDGET WORKBOOK
A3: Step | B3: What to do | C3: Where | D3: Important detail
A4: 1 | B4: Set the budget month and minimum checking buffer. | C4: Setup | D4: Use the first day of the month, such as 12/1/2020.
A5: 2 | B5: Enter up to seven income sources and choose each payment frequency. | C5: Setup | D5: Monthly Equivalent calculates automatically.
A6: 3 | B6: Enter planned amounts, priorities, due days, and fixed/variable status. | C6: Budget Plan | D6: Blue-font cells are intended for user input.
A7: 4 | B7: Paste a bank export into columns A:G without changing the headers. | C7: bk_download | D7: You may paste thousands of rows. Formulas in H:P standardize the data.
A8: 5 | B8: Review Budget Category, Subcategory, and Include? on imported transactions. | C8: bk_download | D8: Transfers and forecasted items default to No. Change misclassified items manually.
A9: 6 | B9: Filter by Month, Category, Account, or Include? to review transactions. | C9: bk_download | D9: Expense Amount converts bank negatives into positive spending.
A10: 7 | B10: Review actual spending, remaining budget, and category variance. | C10: Budget Plan / Monthly Summary | D10: Actuals are pulled directly from included bank transactions.
A11: 8 | B11: Enter debt balances, APRs, minimums, and due dates. | C11: Debts | D11: The selected strategy ranks debts and assigns available extra cash.
A12: 9 | B12: Enter savings goals and planned monthly contributions. | C12: Goals | D12: The sheet calculates required savings and feasibility.
A13: 10 | B13: Use the Dashboard for payment order and financial-health warnings. | C13: Dashboard | D13: Recommendations depend on the completeness of income, budget, debt, and goal inputs.
A15: Color | B15: Meaning
A16: Blue text | B16: User-entered assumptions or editable inputs
A17: Green text | B17: Formula linked to another worksheet
A18: Black text | B18: Formula or calculation
A19: Yellow fill | B19: Key setting that should be reviewed
A21: Bank Import Notes
A22: Supported structure | B22: The existing bank export uses status, date, transaction description, category, and amount.
A23: Different bank formats | B23: Rearrange the exported columns to match A:G or paste into the corresponding columns.
A24: Duplicates | B24: Possible duplicate rows are flagged in Review Note. Set Include? to No for any confirmed duplicate.
A25: MANUAL ACTUALS WORKFLOW
A26: 1 | B26: During the month | C26: Enter spending in Manual Actuals. Use positive expense amounts, select category/subcategory, and set Include? to Yes.
A27: 2 | B27: Live reporting | C27: Keep Setup!B8 set to Manual (Live). Dashboard and Budget Plan use manual entries immediately.
A28: 3 | B28: Month-end import | C28: Paste the bank export into bk_download and review the mapped categories and Include? flags.
A29: 4 | B29: Reconcile | C29: Use the Reconciliation sheet to compare manual entries against bank totals by category.
A30: 5 | B30: Close the month | C30: After differences are resolved, change Setup!B8 to Bank (Closed). Reports then use bank transactions as final actuals.
A31: 6 | B31: No double counting | C31: The source selector chooses manual OR bank actuals; it does not add them together.

Sheet Dashboard
A1: HOUSEHOLD FINANCIAL DASHBOARD
A3: ="Reporting Month: "&TEXT(Setup!B4,"mmmm yyyy")&" | Actuals: "&Setup!B8 -> Reporting Month: August 2026 | Actuals: Manual (Live)
A5: Monthly Income | D5: Planned Expenses | G5: Actual Expenses (Selected Source) | J5: Actual Cash Flow
A6: =Setup!H11 -> 18796.13 | D6: ='Budget Plan'!C57 -> 15915.13 | G6: ='Budget Plan'!D57 -> 0 | J6: =B5-G6 -> 0
A9: Planned Surplus | D9: Total Debt | G9: Goal Contributions | J9: Available for Extra Debt
A10: =B6-E6 -> 0 | D10: =Debts!B14 -> 0 | G10: =SUM(Goals!H4:H9) -> 375 | J10: =MAX(0,B6-G6-K10) -> 0
A13: PAYMENT PRIORITY RECOMMENDATION | H13: Category | I13: Planned | J13: Actual | K13: Remaining
A14: Priority | B14: Action | C14: Amount ($) | D14: Timing | E14: Reason | F14: Status | H14: Housing | I14: =SUMIF('Monthly Summary'!$A$4:$A$20,H14,'Monthly Summary'!$B$4:$B$20) -> 2669.78 | J14: =SUMIF('Monthly Summary'!$A$4:$A$20,H14,'Monthly Summary'!$C$4:$C$20) -> 545.9 | K14: =I14-J14 -> 2123.88
A15: 1 | B15: Cover all essential and fixed expenses | C15: =SUMIFS('Budget Plan'!$C$4:$C$55,'Budget Plan'!$G$4:$G$55,"Critical")+SUMIFS('Budget Plan'!$C$4:$C$55,'Budget Plan'!$H$4:$H$55,"Fixed") -> 8045.25 | D15: Before due dates | E15: Avoid missed bills and fees | F15: =IF(B6>=C15,"Funded","Shortfall") -> Shortfall | H15: Utilities | I15: =SUMIF('Monthly Summary'!$A$4:$A$20,H15,'Monthly Summary'!$B$4:$B$20) -> 2149.88 | J15: =SUMIF('Monthly Summary'!$A$4:$A$20,H15,'Monthly Summary'!$C$4:$C$20) -> 121 | K15: =I15-J15 -> 2028.88
A16: 2 | B16: Maintain checking buffer | C16: =Setup!B5 -> 500 | D16: Throughout month | E16: Prevent overdraft | F16: =IF(B6-G6>=C16,"Protected","At Risk") -> At Risk | H16: Vehicle | I16: =SUMIF('Monthly Summary'!$A$4:$A$20,H16,'Monthly Summary'!$B$4:$B$20) -> 2962.51 | J16: =SUMIF('Monthly Summary'!$A$4:$A$20,H16,'Monthly Summary'!$C$4:$C$20) -> 1489.84 | K16: =I16-J16 -> 1472.67
A17: 3 | B17: Pay all debt minimums | C17: =Debts!B15 -> 0 | D17: By due dates | E17: Protect credit and avoid penalties | F17: =IF(B6>=C15+C17,"Funded","Review") -> Review | H17: Food | I17: =SUMIF('Monthly Summary'!$A$4:$A$20,H17,'Monthly Summary'!$B$4:$B$20) -> 1300 | J17: =SUMIF('Monthly Summary'!$A$4:$A$20,H17,'Monthly Summary'!$C$4:$C$20) -> 20.47 | K17: =I17-J17 -> 1279.53
A18: 4 | B18: Fund savings goals | C18: =SUM(Goals!H4:H9) -> 375 | D18: After essentials | E18: Maintain goal progress | F18: =IF(B6-G6-C17>=C18,"Funded","Reduce/Delay") -> Reduce/Delay | H18: Debt | I18: =SUMIF('Monthly Summary'!$A$4:$A$20,H18,'Monthly Summary'!$B$4:$B$20) -> 619.89 | J18: =SUMIF('Monthly Summary'!$A$4:$A$20,H18,'Monthly Summary'!$C$4:$C$20) -> 289.12 | K18: =I18-J18 -> 330.77
A19: 5 | B19: Send remaining surplus to top-ranked debt | C19: =MAX(0,B10-Setup!B5) -> 0 | D19: After all above | E19: Reduce interest and payoff time | F19: =IF(C19>0,"Recommended","No extra available") -> No extra available | H19: Savings | I19: =SUMIF('Monthly Summary'!$A$4:$A$20,H19,'Monthly Summary'!$B$4:$B$20) -> 90 | J19: =SUMIF('Monthly Summary'!$A$4:$A$20,H19,'Monthly Summary'!$C$4:$C$20) -> 0 | K19: =I19-J19 -> 90
H20: Entertainment | I20: =SUMIF('Monthly Summary'!$A$4:$A$20,H20,'Monthly Summary'!$B$4:$B$20) -> 1000 | J20: =SUMIF('Monthly Summary'!$A$4:$A$20,H20,'Monthly Summary'!$C$4:$C$20) -> 0 | K20: =I20-J20 -> 1000
H21: Subscriptions | I21: =SUMIF('Monthly Summary'!$A$4:$A$20,H21,'Monthly Summary'!$B$4:$B$20) -> 1600 | J21: =SUMIF('Monthly Summary'!$A$4:$A$20,H21,'Monthly Summary'!$C$4:$C$20) -> 377.77 | K21: =I21-J21 -> 1222.23
A22: FINANCIAL HEALTH FLAGS | H22: Miscellaneous | I22: =SUMIF('Monthly Summary'!$A$4:$A$20,H22,'Monthly Summary'!$B$4:$B$20) -> 2800 | J22: =SUMIF('Monthly Summary'!$A$4:$A$20,H22,'Monthly Summary'!$C$4:$C$20) -> 921.75 | K22: =I22-J22 -> 1878.25
A23: Metric | B23: Current | C23: Target | D23: Status | E23: Recommended Action | F23: Notes
A24: Savings Rate | B24: =IF(B6=0,0,SUMIFS('Budget Plan'!$D$4:$D$55,'Budget Plan'!$A$4:$A$55,"Savings")/B6) -> 0 | C24: 0.1 | D24: =IF(B24>=C24,"Healthy","Below target") -> Below target | E24: Increase goal contributions if below target
A25: Debt Payment Ratio | B25: =IF(B6=0,0,Debts!B15/B6) -> 0 | C25: 0.2 | D25: =IF(B25<=C25,"Healthy","High") -> Healthy | E25: Reduce debt burden if above target
A26: Housing Ratio | B26: =IF(B6=0,0,SUMIFS('Budget Plan'!$D$4:$D$55,'Budget Plan'!$A$4:$A$55,"Housing")/B6) -> 0 | C26: 0.3 | D26: =IF(B26<=C26,"Healthy","High") -> Healthy | E26: Review housing costs if above target
A27: Emergency Fund Months | B27: =IF(SUMIFS('Budget Plan'!$D$4:$D$55,'Budget Plan'!$G$4:$G$55,"Critical")=0,0,Goals!D4/SUMIFS('Budget Plan'!$D$4:$D$55,'Budget Plan'!$G$4:$G$55,"Critical")) -> 0 | C27: =Setup!B7 -> 3 | D27: =IF(B27>=C27,"Healthy","Below target") -> Below target | E27: Build emergency savings
A28: Budget Variance | B28: ='Budget Plan'!E57 -> 15915.13 | C28: 0 | D28: =IF(B28>=C28,"On budget","Over budget") -> On budget | E28: Review categories over budget

Sheet Setup
A1: HOUSEHOLD BUDGET CONTROL CENTER | I1: Subcategory Lists → | J1: Housing | K1: Utilities | L1: Vehicle | M1: Food | N1: Insurance | O1: Medical | P1: Children | Q1: Personal Care | R1: Entertainment | S1: Subscriptions | T1: Giving | U1: Pets | V1: Debt | W1: Savings | X1: Taxes | Y1: Legal | Z1: Account → | AA1: Account
J2: Mortgage/Rent | K2: Electricity | L2: Car Payment | M2: Groceries | N2: Life Insurance | O2: Healthcare | P2: Child/Dependent | Q2: Personal Care | R2: Entertainment | S2: Streaming | T2: Tithe/Charity | U2: Pet Care | V2: Loans | W2: Emergency Fund | X2: Federal/State/Local | Y2: Legal | Z2: Cash/ATM | AA2: Checking
A3: Core Settings | B3: Value | D3: Income Source | E3: Owner | F3: Frequency | G3: Net Amount ($) | H3: Monthly Equivalent ($) | J3: Property Taxes | K3: Water/Sewer/Trash | L3: Auto Insurance | M3: Dining Out | N3: Disability/Other | O3: Prescriptions | P3: School/Activities | Q3: Clothing | R3: Online Services | S3: Music | T3: Gifts | V3: Credit Cards | W3: General Savings | Z3: General Merchandise | AA3: Savings
A4: Selected Budget Month | B4: August 2026 | D4: Income 1 | E4: Household | F4: Monthly | G4: 3938.58 | H4: =IF(G4="","",G4*IF(F4="Weekly",52/12,IF(F4="Biweekly",26/12,IF(F4="Semimonthly",2,IF(F4="Monthly",1,IF(F4="Quarterly",1/3,IF(F4="Annual",1/12,1))))))) -> 3938.58 | J4: Home Insurance | K4: Internet | L4: Fuel | M4: Household Supplies | O4: Dental/Vision | Q4: Hair/Nails | R4: Subscriptions | S4: Software/Apps | V4: Other Debt | W4: Retirement | Z4: Other
A5: Minimum Checking Buffer | B5: 500 | D5: Income 2 | E5: Household | F5: Monthly | G5: 758.37 | H5: 758.37 | J5: HOA | K5: Telephone | L5: Maintenance/Repairs | S5: Other Subscriptions | W5: College | Z5: Uncategorized
A6: Debt Strategy | B6: Avalanche | D6: Income 3 | E6: Household | F6: Monthly | G6: 2240 | H6: 2240 | J6: Home Maintenance | K6: Gas | L6: Registration/Tolls
A7: Emergency Fund Target (months) | B7: 3 | D7: Income 4 | E7: Household | F7: Monthly | G7: 4275.17 | H7: 4275.17 | J7: Home Improvement
A8: Actuals Source Mode | B8: Manual (Live) | D8: Income 5 | E8: Household | F8: Monthly | G8: 4078.45 | H8: 4078.45
D9: Income 6 | E9: Household | F9: Monthly | G9: 1752.78 | H9: 1752.78
A10: Budget Category | B10: Default Subcategory | C10: Active | D10: Income 7 | E10: Household | F10: Monthly | G10: 1752.78 | H10: 1752.78
A11: Housing | B11: Mortgage/Rent | C11: Yes | D11: Total Monthly Income | H11: =SUM(H4:H10) -> 18796.13
A12: Utilities | B12: Electricity | C12: Yes
A13: Vehicle | B13: Car Payment | C13: Yes
A14: Food | B14: Groceries | C14: Yes | E14: Bank Category | F14: Budget Category | G14: Subcategory
A15: Insurance | B15: Home/Life/Other | C15: Yes | E15: Mortgages | F15: Housing | G15: Mortgage/Rent
A16: Medical | B16: Healthcare | C16: Yes | E16: Home Maintenance | F16: Housing | G16: Home Maintenance
A17: Children | B17: Child/Dependent | C17: Yes | E17: Home Improvement | F17: Housing | G17: Home Improvement
A18: Personal Care | B18: Personal Care | C18: Yes | E18: Century Link | F18: Utilities | G18: Internet
A19: Entertainment | B19: Subscriptions | C19: Yes | E19: Just Energy | F19: Utilities | G19: Electricity
A20: Subscriptions | B20: Streaming | C20: Yes | E20: Killeen Utilities | F20: Utilities | G20: Water/Sewer/Trash
A21: Giving | B21: Tithe/Charity | C21: Yes | E21: Telephone Services | F21: Utilities | G21: Telephone
A22: Pets | B22: Pet Care | C22: Yes | E22: Car Payment | F22: Vehicle | G22: Car Payment
A23: Debt | B23: Loans/Credit Cards | C23: Yes | E23: Automotive Expenses | F23: Vehicle | G23: Maintenance/Repairs
A24: Savings | B24: Savings/Investments | C24: Yes | E24: Gasoline/Fuel | F24: Vehicle | G24: Fuel
A25: Taxes | B25: Taxes | C25: Yes | E25: Groceries | F25: Food | G25: Groceries
... A29: Transfers | B29: Transfers | C29: No | E29: Child/Dependent Expenses | F29: Children | G29: Child/Dependent
E30: Clothing/Shoes | F30: Personal Care | G30: Clothing
E31: Personal Care | F31: Personal Care | G31: Personal Care
E32: Entertainment | F32: Entertainment | G32: Entertainment
E33: Online Services | F33: Entertainment | G33: Online Services
E34: Pets/Pet Care | F34: Pets | G34: Pet Care
E35: Loans | F35: Debt | G35: Loans
E36: ATM/Cash Withdrawals | F36: Miscellaneous | G36: Cash/ATM
E37: General Merchandise | F37: Miscellaneous | G37: General Merchandise
E38: Other Expenses | F38: Miscellaneous | G38: Other
E39: Uncategorized | F39: Miscellaneous | G39: Uncategorized
E40: Other Income | F40: Income | G40: Other Income
E41: Transfers | F41: Transfers | G41: Transfers
... E79: Utilities | F79: Utilities | G79: Electricity

Sheet Budget Plan
A1: MONTHLY BUDGET PLAN — LIVE ACTUALS & MONTH-END RECONCILIATION
A3: Category | B3: Subcategory | C3: Planned ($) | D3: Actual Used ($) | E3: Remaining ($) | F3: Variance % | G3: Priority | H3: Fixed/Variable | I3: Due Day | J3: Notes | K3: Manual Actual ($) | L3: Bank Actual ($) | M3: Recon Difference ($)
A4: Housing | B4: Mortgage/Rent | C4: =1396.87+767+406.91 -> 2570.78 | D4: =IF(Setup!$B$8="Bank (Closed)",L4,K4) -> 406.91 | E4: =C4-D4 -> 2163.87 | F4: =IF(C4=0,IF(D4=0,0,-1),(C4-D4)/C4) -> 0.8417173 | G4: Medium | H4: Fixed | K4: =SUMIFS('Manual Actuals'!$C$2:$C$861,'Manual Actuals'!$D$2:$D$861,$A4,'Manual Actuals'!$E$2:$E$861,$B4,'Manual Actuals'!$H$2:$H$861,Setup!$B$4,'Manual Actuals'!$G$2:$G$861,"Yes") -> 406.91 | L4: =SUMIFS(bk_download!$L$2:$L$1902,bk_download!$H$2:$H$1902,$A4,bk_download!$I$2:$I$1902,$B4,bk_download!$K$2:$K$1902,Setup!$B$4,bk_download!$J$2:$J$1902,"Yes") -> 0 | M4: =K4-L4 -> 406.91
A5: Housing | B5: Property Taxes | C5: 0 | D5: =IF(Setup!$B$8="Bank (Closed)",L5,K5) -> 0 | E5: =C5-D5 -> 0 | F5: =IF(C5=0,IF(D5=0,0,-1),(C5-D5)/C5) -> 0 | G5: Medium | H5: Variable | J5: Exempt due to status | K5: =SUMIFS('Manual Actuals'!$C$2:$C$861,'Manual Actuals'!$D$2:$D$861,$A5,'Manual Actuals'!$E$2:$E$861,$B5,'Manual Actuals'!$H$2:$H$861,Setup!$B$4,'Manual Actuals'!$G$2:$G$861,"Yes") -> 0 | L5: =SUMIFS(bk_download!$L$2:$L$1902,bk_download!$H$2:$H$1902,$A5,bk_download!$I$2:$I$1902,$B5,bk_download!$K$2:$K$1902,Setup!$B$4,bk_download!$J$2:$J$1902,"Yes") -> 0 | M5: =K5-L5 -> 0
A6: Housing | B6: Home Insurance | C6: 0 | D6: =IF(Setup!$B$8="Bank (Closed)",L6,K6) -> 138.99 | E6: =C6-D6 -> -138.99 | F6: =IF(C6=0,IF(D6=0,0,-1),(C6-D6)/C6) -> -1 | G6: Medium | H6: Variable | J6: Included in mortgage payment | K6: =SUMIFS('Manual Actuals'!$C$2:$C$861,'Manual Actuals'!$D$2:$D$861,$A6,'Manual Actuals'!$E$2:$E$861,$B6,'Manual Actuals'!$H$2:$H$861,Setup!$B$4,'Manual Actuals'!$G$2:$G$861,"Yes") -> 138.99 | L6: =SUMIFS(bk_download!$L$2:$L$1902,bk_download!$H$2:$H$1902,$A6,bk_download!$I$2:$I$1902,$B6,bk_download!$K$2:$K$1902,Setup!$B$4,bk_download!$J$2:$J$1902,"Yes") -> 0 | M6: =K6-L6 -> 138.99
A7: Housing | B7: HOA | C7: 99 | D7: =IF(Setup!$B$8="Bank (Closed)",L7,K7) -> 0 | E7: =C7-D7 -> 99 | F7: =IF(C7=0,IF(D7=0,0,-1),(C7-D7)/C7) -> 1 | G7: Medium | H7: Fixed | K7: =SUMIFS('Manual Actuals'!$C$2:$C$861,'Manual Actuals'!$D$2:$D$861,$A7,'Manual Actuals'!$E$2:$E$861,$B7,'Manual Actuals'!$H$2:$H$861,Setup!$B$4,'Manual Actuals'!$G$2:$G$861,"Yes") -> 0 | L7: =SUMIFS(bk_download!$L$2:$L$1902,bk_download!$H$2:$H$1902,$A7,bk_download!$I$2:$I$1902,$B7,bk_download!$K$2:$K$1902,Setup!$B$4,bk_download!$J$2:$J$1902,"Yes") -> 0 | M7: =K7-L7 -> 0
A8: Housing | B8: Home Maintenance | C8: 0 | D8: =IF(Setup!$B$8="Bank (Closed)",L8,K8) -> 0 | E8: =C8-D8 -> 0 | F8: =IF(C8=0,IF(D8=0,0,-1),(C8-D8)/C8) -> 0 | G8: Medium | H8: Variable | K8: =SUMIFS('Manual Actuals'!$C$2:$C$861,'Manual Actuals'!$D$2:$D$861,$A8,'Manual Actuals'!$E$2:$E$861,$B8,'Manual Actuals'!$H$2:$H$861,Setup!$B$4,'Manual Actuals'!$G$2:$G$861,"Yes") -> 0 | L8: =SUMIFS(bk_download!$L$2:$L$1902,bk_download!$H$2:$H$1902,$A8,bk_download!$I$2:$I$1902,$B8,bk_download!$K$2:$K$1902,Setup!$B$4,bk_download!$J$2:$J$1902,"Yes") -> 0 | M8: =K8-L8 -> 0
A9: Housing | B9: Home Improvement | C9: 0 | D9: =IF(Setup!$B$8="Bank (Closed)",L9,K9) -> 0 | E9: =C9-D9 -> 0 | F9: =IF(C9=0,IF(D9=0,0,-1),(C9-D9)/C9) -> 0 | G9: Medium | H9: Variable | K9: =SUMIFS('Manual Actuals'!$C$2:$C$861,'Manual Actuals'!$D$2:$D$861,$A9,'Manual Actuals'!$E$2:$E$861,$B9,'Manual Actuals'!$H$2:$H$861,Setup!$B$4,'Manual Actuals'!$G$2:$G$861,"Yes") -> 0 | L9: =SUMIFS(bk_download!$L$2:$L$1902,bk_download!$H$2:$H$1902,$A9,bk_download!$I$2:$I$1902,$B9,bk_download!$K$2:$K$1902,Setup!$B$4,bk_download!$J$2:$J$1902,"Yes") -> 0 | M9: =K9-L9 -> 0
A10: Utilities | B10: Electricity | C10: =326+508+140 -> 974 | D10: =IF(Setup!$B$8="Bank (Closed)",L10,K10) -> 0 | E10: =C10-D10 -> 974 | F10: =IF(C10=0,IF(D10=0,0,-1),(C10-D10)/C10) -> 1 | G10: Medium | H10: Variable | J10: Three sources | K10: =SUMIFS('Manual Actuals'!$C$2:$C$861,'Manual Actuals'!$D$2:$D$861,$A10,'Manual Actuals'!$E$2:$E$861,$B10,'Manual Actuals'!$H$2:$H$861,Setup!$B$4,'Manual Actuals'!$G$2:$G$861,"Yes") -> 0 | L10: =SUMIFS(bk_download!$L$2:$L$1902,bk_download!$H$2:$H$1902,$A10,bk_download!$I$2:$I$1902,$B10,bk_download!$K$2:$K$1902,Setup!$B$4,bk_download!$J$2:$J$1902,"Yes") -> 0 | M10: =K10-L10 -> 0
A11: Utilities | B11: Water/Sewer/Trash | C11: =188.88+87+100 -> 375.88 | D11: =IF(Setup!$B$8="Bank (Closed)",L11,K11) -> 121 | E11: =C11-D11 -> 254.88 | F11: =IF(C11=0,IF(D11=0,0,-1),(C11-D11)/C11) -> 0.67808875 | G11: Medium | H11: Variable | J11: Three sources | K11: =SUMIFS('Manual Actuals'!$C$2:$C$861,'Manual Actuals'!$D$2:$D$861,$A11,'Manual Actuals'!$E$2:$E$861,$B11,'Manual Actuals'!$H$2:$H$861,Setup!$B$4,'Manual Actuals'!$G$2:$G$861,"Yes") -> 121 | L11: =SUMIFS(bk_download!$L$2:$L$1902,bk_download!$H$2:$H$1902,$A11,bk_download!$I$2:$I$1902,$B11,bk_download!$K$2:$K$1902,Setup!$B$4,bk_download!$J$2:$J$1902,"Yes") -> 0 | M11: =K11-L11 -> 121
A12: Utilities | B12: Internet | C12: 200 | D12: =IF(Setup!$B$8="Bank (Closed)",L12,K12) -> 0 | E12: =C12-D12 -> 200 | F12: =IF(C12=0,IF(D12=0,0,-1),(C12-D12)/C12) -> 1 | G12: Medium | H12: Fixed | K12: =SUMIFS('Manual Actuals'!$C$2:$C$861,'Manual Actuals'!$D$2:$D$861,$A12,'Manual Actuals'!$E$2:$E$861,$B12,'Manual Actuals'!$H$2:$H$861,Setup!$B$4,'Manual Actuals'!$G$2:$G$861,"Yes") -> 0 | L12: =SUMIFS(bk_download!$L$2:$L$1902,bk_download!$H$2:$H$1902,$A12,bk_download!$I$2:$I$1902,$B12,bk_download!$K$2:$K$1902,Setup!$B$4,bk_download!$J$2:$J$1902,"Yes") -> 0 | M12: =K12-L12 -> 0
A13: Utilities | B13: Telephone | C13: 500 | D13: =IF(Setup!$B$8="Bank (Closed)",L13,K13) -> 0 | E13: =C13-D13 -> 500 | F13: =IF(C13=0,IF(D13=0,0,-1),(C13-D13)/C13) -> 1 | G13: Medium | H13: Variable | J13: Two sources | K13: =SUMIFS('Manual Actuals'!$C$2:$C$861,'Manual Actuals'!$D$2:$D$861,$A13,'Manual Actuals'!$E$2:$E$861,$B13,'Manual Actuals'!$H$2:$H$861,Setup!$B$4,'Manual Actuals'!$G$2:$G$861,"Yes") -> 0 | L13: =SUMIFS(bk_download!$L$2:$L$1902,bk_download!$H$2:$H$1902,$A13,bk_download!$I$2:$I$1902,$B13,bk_download!$K$2:$K$1902,Setup!$B$4,bk_download!$J$2:$J$1902,"Yes") -> 0 | M13: =K13-L13 -> 0
A14: Utilities | B14: Gas | C14: 100 | D14: =IF(Setup!$B$8="Bank (Closed)",L14,K14) -> 0 | E14: =C14-D14 -> 100 | F14: =IF(C14=0,IF(D14=0,0,-1),(C14-D14)/C14) -> 1 | G14: Medium | H14: Variable | K14: =SUMIFS('Manual Actuals'!$C$2:$C$861,'Manual Actuals'!$D$2:$D$861,$A14,'Manual Actuals'!$E$2:$E$861,$B14,'Manual Actuals'!$H$2:$H$861,Setup!$B$4,'Manual Actuals'!$G$2:$G$861,"Yes") -> 0 | L14: =SUMIFS(bk_download!$L$2:$L$1902,bk_download!$H$2:$H$1902,$A14,bk_download!$I$2:$I$1902,$B14,bk_download!$K$2:$K$1902,Setup!$B$4,bk_download!$J$2:$J$1902,"Yes") -> 0 | M14: =K14-L14 -> 0
A15: Vehicle | B15: Car Payment | C15: =600+1459.84 -> 2059.84 | D15: =IF(Setup!$B$8="Bank (Closed)",L15,K15) -> 1459.84 | E15: =C15-D15 -> 600 | F15: =IF(C15=0,IF(D15=0,0,-1),(C15-D15)/C15) -> 0.29128476 | G15: Medium | H15: Fixed | J15: Two sources | K15: =SUMIFS('Manual Actuals'!$C$2:$C$861,'Manual Actuals'!$D$2:$D$861,$A15,'Manual Actuals'!$E$2:$E$861,$B15,'Manual Actuals'!$H$2:$H$861,Setup!$B$4,'Manual Actuals'!$G$2:$G$861,"Yes") -> 1459.84 | L15: =SUMIFS(bk_download!$L$2:$L$1902,bk_download!$H$2:$H$1902,$A15,bk_download!$I$2:$I$1902,$B15,bk_download!$K$2:$K$1902,Setup!$B$4,bk_download!$J$2:$J$1902,"Yes") -> 0 | M15: =K15-L15 -> 1459.84
A16: Vehicle | B16: Auto Insurance | C16: =411.19+274.48+157 -> 842.67 | D16: =IF(Setup!$B$8="Bank (Closed)",L16,K16) -> 0 | E16: =C16-D16 -> 842.67 | F16: =IF(C16=0,IF(D16=0,0,-1),(C16-D16)/C16) -> 1 | G16: Medium | H16: Fixed | J16: Two sources | K16: =SUMIFS('Manual Actuals'!$C$2:$C$861,'Manual Actuals'!$D$2:$D$861,$A16,'Manual Actuals'!$E$2:$E$861,$B16,'Manual Actuals'!$H$2:$H$861,Setup!$B$4,'Manual Actuals'!$G$2:$G$861,"Yes") -> 0 | L16: =SUMIFS(bk_download!$L$2:$L$1902,bk_download!$H$2:$H$1902,$A16,bk_download!$I$2:$I$1902,$B16,bk_download!$K$2:$K$1902,Setup!$B$4,bk_download!$J$2:$J$1902,"Yes") -> 0 | M16: =K16-L16 -> 0
A17: Vehicle | B17: Fuel | C17: 60 | D17: =IF(Setup!$B$8="Bank (Closed)",L17,K17) -> 30 | E17: =C17-D17 -> 30 | F17: =IF(C17=0,IF(D17=0,0,-1),(C17-D17)/C17) -> 0.5 | G17: Medium | H17: Variable | K17: =SUMIFS('Manual Actuals'!$C$2:$C$861,'Manual Actuals'!$D$2:$D$861,$A17,'Manual Actuals'!$E$2:$E$861,$B17,'Manual Actuals'!$H$2:$H$861,Setup!$B$4,'Manual Actuals'!$G$2:$G$861,"Yes") -> 30 | L17: =SUMIFS(bk_download!$L$2:$L$1902,bk_download!$H$2:$H$1902,$A17,bk_download!$I$2:$I$1902,$B17,bk_download!$K$2:$K$1902,Setup!$B$4,bk_download!$J$2:$J$1902,"Yes") -> 0 | M17: =K17-L17 -> 30
A18: Vehicle | B18: Maintenance/Repairs | D18: =IF(Setup!$B$8="Bank (Closed)",L18,K18) -> 0 | E18: =C18-D18 -> 0 | F18: =IF(C18=0,IF(D18=0,0,-1),(C18-D18)/C18) -> 0 | G18: Medium | H18: Variable | K18: =SUMIFS('Manual Actuals'!$C$2:$C$861,'Manual Actuals'!$D$2:$D$861,$A18,'Manual Actuals'!$E$2:$E$861,$B18,'Manual Actuals'!$H$2:$H$861,Setup!$B$4,'Manual Actuals'!$G$2:$G$861,"Yes") -> 0 | L18: =SUMIFS(bk_download!$L$2:$L$1902,bk_download!$H$2:$H$1902,$A18,bk_download!$I$2:$I$1902,$B18,bk_download!$K$2:$K$1902,Setup!$B$4,bk_download!$J$2:$J$1902,"Yes") -> 3.97 | M18: =K18-L18 -> -3.97
A19: Vehicle | B19: Registration/Tolls | D19: =IF(Setup!$B$8="Bank (Closed)",L19,K19) -> 0 | E19: =C19-D19 -> 0 | F19: =IF(C19=0,IF(D19=0,0,-1),(C19-D19)/C19) -> 0 | G19: Medium | H19: Variable | K19: =SUMIFS('Manual Actuals'!$C$2:$C$861,'Manual Actuals'!$D$2:$D$861,$A19,'Manual Actuals'!$E$2:$E$861,$B19,'Manual Actuals'!$H$2:$H$861,Setup!$B$4,'Manual Actuals'!$G$2:$G$861,"Yes") -> 0 | L19: =SUMIFS(bk_download!$L$2:$L$1902,bk_download!$H$2:$H$1902,$A19,bk_download!$I$2:$I$1902,$B19,bk_download!$K$2:$K$1902,Setup!$B$4,bk_download!$J$2:$J$1902,"Yes") -> 0 | M19: =K19-L19 -> 0
A20: Food | B20: Groceries | C20: 800 | D20: =IF(Setup!$B$8="Bank (Closed)",L20,K20) -> 0 | E20: =C20-D20 -> 800 | F20: =IF(C20=0,IF(D20=0,0,-1),(C20-D20)/C20) -> 1 | G20: Medium | H20: Variable | K20: =SUMIFS('Manual Actuals'!$C$2:$C$861,'Manual Actuals'!$D$2:$D$861,$A20,'Manual Actuals'!$E$2:$E$861,$B20,'Manual Actuals'!$H$2:$H$861,Setup!$B$4,'Manual Actuals'!$G$2:$G$861,"Yes") -> 0 | L20: =SUMIFS(bk_download!$L$2:$L$1902,bk_download!$H$2:$H$1902,$A20,bk_download!$I$2:$I$1902,$B20,bk_download!$K$2:$K$1902,Setup!$B$4,bk_download!$J$2:$J$1902,"Yes") -> 0 | M20: =K20-L20 -> 0
A21: Food | B21: Dining Out | C21: 500 | D21: =IF(Setup!$B$8="Bank (Closed)",L21,K21) -> 20.47 | E21: =C21-D21 -> 479.53 | F21: =IF(C21=0,IF(D21=0,0,-1),(C21-D21)/C21) -> 0.95906 | G21: Medium | H21: Variable | K21: =SUMIFS('Manual Actuals'!$C$2:$C$861,'Manual Actuals'!$D$2:$D$861,$A21,'Manual Actuals'!$E$2:$E$861,$B21,'Manual Actuals'!$H$2:$H$861,Setup!$B$4,'Manual Actuals'!$G$2:$G$861,"Yes") -> 20.47 | L21: =SUMIFS(bk_download!$L$2:$L$1902,bk_download!$H$2:$H$1902,$A21,bk_download!$I$2:$I$1902,$B21,bk_download!$K$2:$K$1902,Setup!$B$4,bk_download!$J$2:$J$1902,"Yes") -> 0 | M21: =K21-L21 -> 20.47
A22: Food | B22: Household Supplies | C22: 0 | D22: =IF(Setup!$B$8="Bank (Closed)",L22,K22) -> 0 | E22: =C22-D22 -> 0 | F22: =IF(C22=0,IF(D22=0,0,-1),(C22-D22)/C22) -> 0 | G22: Medium | H22: Variable | K22: =SUMIFS('Manual Actuals'!$C$2:$C$861,'Manual Actuals'!$D$2:$D$861,$A22,'Manual Actuals'!$E$2:$E$861,$B22,'Manual Actuals'!$H$2:$H$861,Setup!$B$4,'Manual Actuals'!$G$2:$G$861,"Yes") -> 0 | L22: =SUMIFS(bk_download!$L$2:$L$1902,bk_download!$H$2:$H$1902,$A22,bk_download!$I$2:$I$1902,$B22,bk_download!$K$2:$K$1902,Setup!$B$4,bk_download!$J$2:$J$1902,"Yes") -> 0 | M22: =K22-L22 -> 0
A23: Insurance | B23: Life Insurance | C23: 0 | D23: =IF(Setup!$B$8="Bank (Closed)",L23,K23) -> 0 | E23: =C23-D23 -> 0 | F23: =IF(C23=0,IF(D23=0,0,-1),(C23-D23)/C23) -> 0 | G23: Medium | H23: Variable | K23: =SUMIFS('Manual Actuals'!$C$2:$C$861,'Manual Actuals'!$D$2:$D$861,$A23,'Manual Actuals'!$E$2:$E$861,$B23,'Manual Actuals'!$H$2:$H$861,Setup!$B$4,'Manual Actuals'!$G$2:$G$861,"Yes") -> 0 | L23: =SUMIFS(bk_download!$L$2:$L$1902,bk_download!$H$2:$H$1902,$A23,bk_download!$I$2:$I$1902,$B23,bk_download!$K$2:$K$1902,Setup!$B$4,bk_download!$J$2:$J$1902,"Yes") -> 0 | M23: =K23-L23 -> 0
A24: Insurance | B24: Disability/Other | C24: 0 | D24: =IF(Setup!$B$8="Bank (Closed)",L24,K24) -> 0 | E24: =C24-D24 -> 0 | F24: =IF(C24=0,IF(D24=0,0,-1),(C24-D24)/C24) -> 0 | G24: Medium | H24: Variable | K24: =SUMIFS('Manual Actuals'!$C$2:$C$861,'Manual Actuals'!$D$2:$D$861,$A24,'Manual Actuals'!$E$2:$E$861,$B24,'Manual Actuals'!$H$2:$H$861,Setup!$B$4,'Manual Actuals'!$G$2:$G$861,"Yes") -> 0 | L24: =SUMIFS(bk_download!$L$2:$L$1902,bk_download!$H$2:$H$1902,$A24,bk_download!$I$2:$I$1902,$B24,bk_download!$K$2:$K$1902,Setup!$B$4,bk_download!$J$2:$J$1902,"Yes") -> 0 | M24: =K24-L24 -> 0
A25: Medical | B25: Healthcare | C25: 0 | D25: =IF(Setup!$B$8="Bank (Closed)",L25,K25) -> 0 | E25: =C25-D25 -> 0 | F25: =IF(C25=0,IF(D25=0,0,-1),(C25-D25)/C25) -> 0 | G25: Medium | H25: Variable | J25: DV Benefit | K25: =SUMIFS('Manual Actuals'!$C$2:$C$861,'Manual Actuals'!$D$2:$D$861,$A25,'Manual Actuals'!$E$2:$E$861,$B25,'Manual Actuals'!$H$2:$H$861,Setup!$B$4,'Manual Actuals'!$G$2:$G$861,"Yes") -> 0 | L25: =SUMIFS(bk_download!$L$2:$L$1902,bk_download!$H$2:$H$1902,$A25,bk_download!$I$2:$I$1902,$B25,bk_download!$K$2:$K$1902,Setup!$B$4,bk_download!$J$2:$J$1902,"Yes") -> 0 | M25: =K25-L25 -> 0
A26: Medical | B26: Prescriptions | C26: 0 | D26: =IF(Setup!$B$8="Bank (Closed)",L26,K26) -> 0 | E26: =C26-D26 -> 0 | F26: =IF(C26=0,IF(D26=0,0,-1),(C26-D26)/C26) -> 0 | G26: Medium | H26: Variable | J26: DV Benefit | K26: =SUMIFS('Manual Actuals'!$C$2:$C$861,'Manual Actuals'!$D$2:$D$861,$A26,'Manual Actuals'!$E$2:$E$861,$B26,'Manual Actuals'!$H$2:$H$861,Setup!$B$4,'Manual Actuals'!$G$2:$G$861,"Yes") -> 0 | L26: =SUMIFS(bk_download!$L$2:$L$1902,bk_download!$H$2:$H$1902,$A26,bk_download!$I$2:$I$1902,$B26,bk_download!$K$2:$K$1902,Setup!$B$4,bk_download!$J$2:$J$1902,"Yes") -> 0 | M26: =K26-L26 -> 0
A27: Medical | B27: Dental/Vision | C27: =40.76+12.31 -> 53.07 | D27: =IF(Setup!$B$8="Bank (Closed)",L27,K27) -> 0 | E27: =C27-D27 -> 53.07 | F27: =IF(C27=0,IF(D27=0,0,-1),(C27-D27)/C27) -> 1 | G27: Medium | H27: Fixed | J27: Dental and Vision for just one source | K27: =SUMIFS('Manual Actuals'!$C$2:$C$861,'Manual Actuals'!$D$2:$D$861,$A27,'Manual Actuals'!$E$2:$E$861,$B27,'Manual Actuals'!$H$2:$H$861,Setup!$B$4,'Manual Actuals'!$G$2:$G$861,"Yes") -> 0 | L27: =SUMIFS(bk_download!$L$2:$L$1902,bk_download!$H$2:$H$1902,$A27,bk_download!$I$2:$I$1902,$B27,bk_download!$K$2:$K$1902,Setup!$B$4,bk_download!$J$2:$J$1902,"Yes") -> 0 | M27: =K27-L27 -> 0
A28: Children | B28: Child/Dependent | C28: 0 | D28: =IF(Setup!$B$8="Bank (Closed)",L28,K28) -> 0 | E28: =C28-D28 -> 0 | F28: =IF(C28=0,IF(D28=0,0,-1),(C28-D28)/C28) -> 0 | G28: Medium | H28: Variable | K28: =SUMIFS('Manual Actuals'!$C$2:$C$861,'Manual Actuals'!$D$2:$D$861,$A28,'Manual Actuals'!$E$2:$E$861,$B28,'Manual Actuals'!$H$2:$H$861,Setup!$B$4,'Manual Actuals'!$G$2:$G$861,"Yes") -> 0 | L28: =SUMIFS(bk_download!$L$2:$L$1902,bk_download!$H$2:$H$1902,$A28,bk_download!$I$2:$I$1902,$B28,bk_download!$K$2:$K$1902,Setup!$B$4,bk_download!$J$2:$J$1902,"Yes") -> 0 | M28: =K28-L28 -> 0
A29: Children | B29: School/Activities | C29: 0 | D29: =IF(Setup!$B$8="Bank (Closed)",L29,K29) -> 0 | E29: =C29-D29 -> 0 | F29: =IF(C29=0,IF(D29=0,0,-1),(C29-D29)/C29) -> 0 | G29: Medium | H29: Variable | K29: =SUMIFS('Manual Actuals'!$C$2:$C$861,'Manual Actuals'!$D$2:$D$861,$A29,'Manual Actuals'!$E$2:$E$861,$B29,'Manual Actuals'!$H$2:$H$861,Setup!$B$4,'Manual Actuals'!$G$2:$G$861,"Yes") -> 0 | L29: =SUMIFS(bk_download!$L$2:$L$1902,bk_download!$H$2:$H$1902,$A29,bk_download!$I$2:$I$1902,$B29,bk_download!$K$2:$K$1902,Setup!$B$4,bk_download!$J$2:$J$1902,"Yes") -> 0 | M29: =K29-L29 -> 0
A30: Personal Care | B30: Personal Care | C30: 120 | D30: =IF(Setup!$B$8="Bank (Closed)",L30,K30) -> 0 | E30: =C30-D30 -> 120 | F30: =IF(C30=0,IF(D30=0,0,-1),(C30-D30)/C30) -> 1 | G30: Medium | H30: Variable | J30: Two sources | K30: =SUMIFS('Manual Actuals'!$C$2:$C$861,'Manual Actuals'!$D$2:$D$861,$A30,'Manual Actuals'!$E$2:$E$861,$B30,'Manual Actuals'!$H$2:$H$861,Setup!$B$4,'Manual Actuals'!$G$2:$G$861,"Yes") -> 0 | L30: =SUMIFS(bk_download!$L$2:$L$1902,bk_download!$H$2:$H$1902,$A30,bk_download!$I$2:$I$1902,$B30,bk_download!$K$2:$K$1902,Setup!$B$4,bk_download!$J$2:$J$1902,"Yes") -> 16.5 | M30: =K30-L30 -> -16.5
A31: Personal Care | B31: Clothing | C31: 0 | D31: =IF(Setup!$B$8="Bank (Closed)",L31,K31) -> 0 | E31: =C31-D31 -> 0 | F31: =IF(C31=0,IF(D31=0,0,-1),(C31-D31)/C31) -> 0 | G31: Medium | H31: Variable | K31: =SUMIFS('Manual Actuals'!$C$2:$C$861,'Manual Actuals'!$D$2:$D$861,$A31,'Manual Actuals'!$E$2:$E$861,$B31,'Manual Actuals'!$H$2:$H$861,Setup!$B$4,'Manual Actuals'!$G$2:$G$861,"Yes") -> 0 | L31: =SUMIFS(bk_download!$L$2:$L$1902,bk_download!$H$2:$H$1902,$A31,bk_download!$I$2:$I$1902,$B31,bk_download!$K$2:$K$1902,Setup!$B$4,bk_download!$J$2:$J$1902,"Yes") -> 0 | M31: =K31-L31 -> 0
A32: Personal Care | B32: Hair/Nails | C32: 350 | D32: =IF(Setup!$B$8="Bank (Closed)",L32,K32) -> 0 | E32: =C32-D32 -> 350 | F32: =IF(C32=0,IF(D32=0,0,-1),(C32-D32)/C32) -> 1 | G32: Medium | H32: Variable | J32: Two sources | K32: =SUMIFS('Manual Actuals'!$C$2:$C$861,'Manual Actuals'!$D$2:$D$861,$A32,'Manual Actuals'!$E$2:$E$861,$B32,'Manual Actuals'!$H$2:$H$861,Setup!$B$4,'Manual Actuals'!$G$2:$G$861,"Yes") -> 0 | L32: =SUMIFS(bk_download!$L$2:$L$1902,bk_download!$H$2:$H$1902,$A32,bk_download!$I$2:$I$1902,$B32,bk_download!$K$2:$K$1902,Setup!$B$4,bk_download!$J$2:$J$1902,"Yes") -> 0 | M32: =K32-L32 -> 0
A33: Entertainment | B33: Entertainment | C33: 400 | D33: =IF(Setup!$B$8="Bank (Closed)",L33,K33) -> 0 | E33: =C33-D33 -> 400 | F33: =IF(C33=0,IF(D33=0,0,-1),(C33-D33)/C33) -> 1 | G33: Medium | H33: Variable | K33: =SUMIFS('Manual Actuals'!$C$2:$C$861,'Manual Actuals'!$D$2:$D$861,$A33,'Manual Actuals'!$E$2:$E$861,$B33,'Manual Actuals'!$H$2:$H$861,Setup!$B$4,'Manual Actuals'!$G$2:$G$861,"Yes") -> 0 | L33: =SUMIFS(bk_download!$L$2:$L$1902,bk_download!$H$2:$H$1902,$A33,bk_download!$I$2:$I$1902,$B33,bk_download!$K$2:$K$1902,Setup!$B$4,bk_download!$J$2:$J$1902,"Yes") -> 0 | M33: =K33-L33 -> 0
A34: Entertainment | B34: Online Services | C34: 300 | D34: =IF(Setup!$B$8="Bank (Closed)",L34,K34) -> 0 | E34: =C34-D34 -> 300 | F34: =IF(C34=0,IF(D34=0,0,-1),(C34-D34)/C34) -> 1 | G34: Medium | H34: Variable | K34: =SUMIFS('Manual Actuals'!$C$2:$C$861,'Manual Actuals'!$D$2:$D$861,$A34,'Manual Actuals'!$E$2:$E$861,$B34,'Manual Actuals'!$H$2:$H$861,Setup!$B$4,'Manual Actuals'!$G$2:$G$861,"Yes") -> 0 | L34: =SUMIFS(bk_download!$L$2:$L$1902,bk_download!$H$2:$H$1902,$A34,bk_download!$I$2:$I$1902,$B34,bk_download!$K$2:$K$1902,Setup!$B$4,bk_download!$J$2:$J$1902,"Yes") -> 0 | M34: =K34-L34 -> 0
A35: Entertainment | B35: Subscriptions | C35: 300 | D35: =IF(Setup!$B$8="Bank (Closed)",L35,K35) -> 0 | E35: =C35-D35 -> 300 | F35: =IF(C35=0,IF(D35=0,0,-1),(C35-D35)/C35) -> 1 | G35: Medium | H35: Variable | K35: =SUMIFS('Manual Actuals'!$C$2:$C$861,'Manual Actuals'!$D$2:$D$861,$A35,'Manual Actuals'!$E$2:$E$861,$B35,'Manual Actuals'!$H$2:$H$861,Setup!$B$4,'Manual Actuals'!$G$2:$G$861,"Yes") -> 0 | L35: =SUMIFS(bk_download!$L$2:$L$1902,bk_download!$H$2:$H$1902,$A35,bk_download!$I$2:$I$1902,$B35,bk_download!$K$2:$K$1902,Setup!$B$4,bk_download!$J$2:$J$1902,"Yes") -> 0 | M35: =K35-L35 -> 0
A36: Subscriptions | B36: Streaming | C36: 400 | D36: =IF(Setup!$B$8="Bank (Closed)",L36,K36) -> 112.11 | E36: =C36-D36 -> 287.89 | F36: =IF(C36=0,IF(D36=0,0,-1),(C36-D36)/C36) -> 0.719725 | G36: Medium | H36: Fixed | K36: =SUMIFS('Manual Actuals'!$C$2:$C$861,'Manual Actuals'!$D$2:$D$861,$A36,'Manual Actuals'!$E$2:$E$861,$B36,'Manual Actuals'!$H$2:$H$861,Setup!$B$4,'Manual Actuals'!$G$2:$G$861,"Yes") -> 112.11 | L36: =SUMIFS(bk_download!$L$2:$L$1902,bk_download!$H$2:$H$1902,$A36,bk_download!$I$2:$I$1902,$B36,bk_download!$K$2:$K$1902,Setup!$B$4,bk_download!$J$2:$J$1902,"Yes") -> 0 | M36: =K36-L36 -> 112.11
A37: Subscriptions | B37: Music | C37: 200 | D37: =IF(Setup!$B$8="Bank (Closed)",L37,K37) -> 0 | E37: =C37-D37 -> 200 | F37: =IF(C37=0,IF(D37=0,0,-1),(C37-D37)/C37) -> 1 | G37: Medium | H37: Fixed | K37: =SUMIFS('Manual Actuals'!$C$2:$C$861,'Manual Actuals'!$D$2:$D$861,$A37,'Manual Actuals'!$E$2:$E$861,$B37,'Manual Actuals'!$H$2:$H$861,Setup!$B$4,'Manual Actuals'!$G$2:$G$861,"Yes") -> 0 | L37: =SUMIFS(bk_download!$L$2:$L$1902,bk_download!$H$2:$H$1902,$A37,bk_download!$I$2:$I$1902,$B37,bk_download!$K$2:$K$1902,Setup!$B$4,bk_download!$J$2:$J$1902,"Yes") -> 0 | M37: =K37-L37 -> 0
A38: Subscriptions | B38: Software/Apps | C38: 500 | D38: =IF(Setup!$B$8="Bank (Closed)",L38,K38) -> 0 | E38: =C38-D38 -> 500 | F38: =IF(C38=0,IF(D38=0,0,-1),(C38-D38)/C38) -> 1 | G38: Medium | H38: Fixed | K38: =SUMIFS('Manual Actuals'!$C$2:$C$861,'Manual Actuals'!$D$2:$D$861,$A38,'Manual Actuals'!$E$2:$E$861,$B38,'Manual Actuals'!$H$2:$H$861,Setup!$B$4,'Manual Actuals'!$G$2:$G$861,"Yes") -> 0 | L38: =SUMIFS(bk_download!$L$2:$L$1902,bk_download!$H$2:$H$1902,$A38,bk_download!$I$2:$I$1902,$B38,bk_download!$K$2:$K$1902,Setup!$B$4,bk_download!$J$2:$J$1902,"Yes") -> 203.99 | M38: =K38-L38 -> -203.99
A39: Subscriptions | B39: Other Subscriptions | C39: 500 | D39: =IF(Setup!$B$8="Bank (Closed)",L39,K39) -> 265.66 | E39: =C39-D39 -> 234.34 | F39: =IF(C39=0,IF(D39=0,0,-1),(C39-D39)/C39) -> 0.46868 | G39: Medium | H39: Fixed | K39: =SUMIFS('Manual Actuals'!$C$2:$C$861,'Manual Actuals'!$D$2:$D$861,$A39,'Manual Actuals'!$E$2:$E$861,$B39,'Manual Actuals'!$H$2:$H$861,Setup!$B$4,'Manual Actuals'!$G$2:$G$861,"Yes") -> 265.66 | L39: =SUMIFS(bk_download!$L$2:$L$1902,bk_download!$H$2:$H$1902,$A39,bk_download!$I$2:$I$1902,$B39,bk_download!$K$2:$K$1902,Setup!$B$4,bk_download!$J$2:$J$1902,"Yes") -> 0 | M39: =K39-L39 -> 265.66
A40: Giving | B40: Tithe/Charity | C40: 0 | D40: =IF(Setup!$B$8="Bank (Closed)",L40,K40) -> 0 | E40: =C40-D40 -> 0 | F40: =IF(C40=0,IF(D40=0,0,-1),(C40-D40)/C40) -> 0 | G40: Medium | H40: Variable | K40: =SUMIFS('Manual Actuals'!$C$2:$C$861,'Manual Actuals'!$D$2:$D$861,$A40,'Manual Actuals'!$E$2:$E$861,$B40,'Manual Actuals'!$H$2:$H$861,Setup!$B$4,'Manual Actuals'!$G$2:$G$861,"Yes") -> 0 | L40: =SUMIFS(bk_download!$L$2:$L$1902,bk_download!$H$2:$H$1902,$A40,bk_download!$I$2:$I$1902,$B40,bk_download!$K$2:$K$1902,Setup!$B$4,bk_download!$J$2:$J$1902,"Yes") -> 0 | M40: =K40-L40 -> 0
A41: Giving | B41: Gifts | C41: 0 | D41: =IF(Setup!$B$8="Bank (Closed)",L41,K41) -> 0 | E41: =C41-D41 -> 0 | F41: =IF(C41=0,IF(D41=0,0,-1),(C41-D41)/C41) -> 0 | G41: Medium | H41: Variable | K41: =SUMIFS('Manual Actuals'!$C$2:$C$861,'Manual Actuals'!$D$2:$D$861,$A41,'Manual Actuals'!$E$2:$E$861,$B41,'Manual Actuals'!$H$2:$H$861,Setup!$B$4,'Manual Actuals'!$G$2:$G$861,"Yes") -> 0 | L41: =SUMIFS(bk_download!$L$2:$L$1902,bk_download!$H$2:$H$1902,$A41,bk_download!$I$2:$I$1902,$B41,bk_download!$K$2:$K$1902,Setup!$B$4,bk_download!$J$2:$J$1902,"Yes") -> 0 | M41: =K41-L41 -> 0
A42: Pets | B42: Pet Care | C42: 200 | D42: =IF(Setup!$B$8="Bank (Closed)",L42,K42) -> 0 | E42: =C42-D42 -> 200 | F42: =IF(C42=0,IF(D42=0,0,-1),(C42-D42)/C42) -> 1 | G42: Medium | H42: Variable | K42: =SUMIFS('Manual Actuals'!$C$2:$C$861,'Manual Actuals'!$D$2:$D$861,$A42,'Manual Actuals'!$E$2:$E$861,$B42,'Manual Actuals'!$H$2:$H$861,Setup!$B$4,'Manual Actuals'!$G$2:$G$861,"Yes") -> 0 | L42: =SUMIFS(bk_download!$L$2:$L$1902,bk_download!$H$2:$H$1902,$A42,bk_download!$I$2:$I$1902,$B42,bk_download!$K$2:$K$1902,Setup!$B$4,bk_download!$J$2:$J$1902,"Yes") -> 0 | M42: =K42-L42 -> 0
A43: Debt | B43: Loans | C43: =191.61+235.06+193.22 -> 619.89 | D43: =IF(Setup!$B$8="Bank (Closed)",L43,K43) -> 289.12 | E43: =C43-D43 -> 330.77 | F43: =IF(C43=0,IF(D43=0,0,-1),(C43-D43)/C43) -> 0.53359467 | G43: Medium | H43: Fixed | J43: Affirm | K43: =SUMIFS('Manual Actuals'!$C$2:$C$861,'Manual Actuals'!$D$2:$D$861,$A43,'Manual Actuals'!$E$2:$E$861,$B43,'Manual Actuals'!$H$2:$H$861,Setup!$B$4,'Manual Actuals'!$G$2:$G$861,"Yes") -> 289.12 | L43: =SUMIFS(bk_download!$L$2:$L$1902,bk_download!$H$2:$H$1902,$A43,bk_download!$I$2:$I$1902,$B43,bk_download!$K$2:$K$1902,Setup!$B$4,bk_download!$J$2:$J$1902,"Yes") -> 0 | M43: =K43-L43 -> 289.12
A44: Debt | B44: Credit Cards | C44: 0 | D44: =IF(Setup!$B$8="Bank (Closed)",L44,K44) -> 0 | E44: =C44-D44 -> 0 | F44: =IF(C44=0,IF(D44=0,0,-1),(C44-D44)/C44) -> 0 | G44: Medium | H44: Variable | K44: =SUMIFS('Manual Actuals'!$C$2:$C$861,'Manual Actuals'!$D$2:$D$861,$A44,'Manual Actuals'!$E$2:$E$861,$B44,'Manual Actuals'!$H$2:$H$861,Setup!$B$4,'Manual Actuals'!$G$2:$G$861,"Yes") -> 0 | L44: =SUMIFS(bk_download!$L$2:$L$1902,bk_download!$H$2:$H$1902,$A44,bk_download!$I$2:$I$1902,$B44,bk_download!$K$2:$K$1902,Setup!$B$4,bk_download!$J$2:$J$1902,"Yes") -> 0 | M44: =K44-L44 -> 0
A45: Debt | B45: Other Debt | C45: 0 | D45: =IF(Setup!$B$8="Bank (Closed)",L45,K45) -> 0 | E45: =C45-D45 -> 0 | F45: =IF(C45=0,IF(D45=0,0,-1),(C45-D45)/C45) -> 0 | G45: Medium | H45: Variable | K45: =SUMIFS('Manual Actuals'!$C$2:$C$861,'Manual Actuals'!$D$2:$D$861,$A45,'Manual Actuals'!$E$2:$E$861,$B45,'Manual Actuals'!$H$2:$H$861,Setup!$B$4,'Manual Actuals'!$G$2:$G$861,"Yes") -> 0 | L45: =SUMIFS(bk_download!$L$2:$L$1902,bk_download!$H$2:$H$1902,$A45,bk_download!$I$2:$I$1902,$B45,bk_download!$K$2:$K$1902,Setup!$B$4,bk_download!$J$2:$J$1902,"Yes") -> 0 | M45: =K45-L45 -> 0
A46: Savings | B46: Emergency Fund | C46: 50 | D46: =IF(Setup!$B$8="Bank (Closed)",L46,K46) -> 0 | E46: =C46-D46 -> 50 | F46: =IF(C46=0,IF(D46=0,0,-1),(C46-D46)/C46) -> 1 | G46: Medium | H46: Variable | K46: =SUMIFS('Manual Actuals'!$C$2:$C$861,'Manual Actuals'!$D$2:$D$861,$A46,'Manual Actuals'!$E$2:$E$861,$B46,'Manual Actuals'!$H$2:$H$861,Setup!$B$4,'Manual Actuals'!$G$2:$G$861,"Yes") -> 0 | L46: =SUMIFS(bk_download!$L$2:$L$1902,bk_download!$H$2:$H$1902,$A46,bk_download!$I$2:$I$1902,$B46,bk_download!$K$2:$K$1902,Setup!$B$4,bk_download!$J$2:$J$1902,"Yes") -> 0 | M46: =K46-L46 -> 0
A47: Savings | B47: General Savings | C47: 20 | D47: =IF(Setup!$B$8="Bank (Closed)",L47,K47) -> 0 | E47: =C47-D47 -> 20 | F47: =IF(C47=0,IF(D47=0,0,-1),(C47-D47)/C47) -> 1 | G47: Medium | H47: Variable | K47: =SUMIFS('Manual Actuals'!$C$2:$C$861,'Manual Actuals'!$D$2:$D$861,$A47,'Manual Actuals'!$E$2:$E$861,$B47,'Manual Actuals'!$H$2:$H$861,Setup!$B$4,'Manual Actuals'!$G$2:$G$861,"Yes") -> 0 | L47: =SUMIFS(bk_download!$L$2:$L$1902,bk_download!$H$2:$H$1902,$A47,bk_download!$I$2:$I$1902,$B47,bk_download!$K$2:$K$1902,Setup!$B$4,bk_download!$J$2:$J$1902,"Yes") -> 0 | M47: =K47-L47 -> 0
A48: Savings | B48: Retirement | C48: 20 | D48: =IF(Setup!$B$8="Bank (Closed)",L48,K48) -> 0 | E48: =C48-D48 -> 20 | F48: =IF(C48=0,IF(D48=0,0,-1),(C48-D48)/C48) -> 1 | G48: Medium | H48: Variable | K48: =SUMIFS('Manual Actuals'!$C$2:$C$861,'Manual Actuals'!$D$2:$D$861,$A48,'Manual Actuals'!$E$2:$E$861,$B48,'Manual Actuals'!$H$2:$H$861,Setup!$B$4,'Manual Actuals'!$G$2:$G$861,"Yes") -> 0 | L48: =SUMIFS(bk_download!$L$2:$L$1902,bk_download!$H$2:$H$1902,$A48,bk_download!$I$2:$I$1902,$B48,bk_download!$K$2:$K$1902,Setup!$B$4,bk_download!$J$2:$J$1902,"Yes") -> 0 | M48: =K48-L48 -> 0
A49: Savings | B49: College | C49: 0 | D49: =IF(Setup!$B$8="Bank (Closed)",L49,K49) -> 0 | E49: =C49-D49 -> 0 | F49: =IF(C49=0,IF(D49=0,0,-1),(C49-D49)/C49) -> 0 | G49: Medium | H49: Variable | K49: =SUMIFS('Manual Actuals'!$C$2:$C$861,'Manual Actuals'!$D$2:$D$861,$A49,'Manual Actuals'!$E$2:$E$861,$B49,'Manual Actuals'!$H$2:$H$861,Setup!$B$4,'Manual Actuals'!$G$2:$G$861,"Yes") -> 0 | L49: =SUMIFS(bk_download!$L$2:$L$1902,bk_download!$H$2:$H$1902,$A49,bk_download!$I$2:$I$1902,$B49,bk_download!$K$2:$K$1902,Setup!$B$4,bk_download!$J$2:$J$1902,"Yes") -> 0 | M49: =K49-L49 -> 0
A50: Taxes | B50: Federal/State/Local | C50: 0 | D50: =IF(Setup!$B$8="Bank (Closed)",L50,K50) -> 0 | E50: =C50-D50 -> 0 | F50: =IF(C50=0,IF(D50=0,0,-1),(C50-D50)/C50) -> 0 | G50: Medium | H50: Variable | K50: =SUMIFS('Manual Actuals'!$C$2:$C$861,'Manual Actuals'!$D$2:$D$861,$A50,'Manual Actuals'!$E$2:$E$861,$B50,'Manual Actuals'!$H$2:$H$861,Setup!$B$4,'Manual Actuals'!$G$2:$G$861,"Yes") -> 0 | L50: =SUMIFS(bk_download!$L$2:$L$1902,bk_download!$H$2:$H$1902,$A50,bk_download!$I$2:$I$1902,$B50,bk_download!$K$2:$K$1902,Setup!$B$4,bk_download!$J$2:$J$1902,"Yes") -> 0 | M50: =K50-L50 -> 0
A51: Legal | B51: Legal | C51: 0 | D51: =IF(Setup!$B$8="Bank (Closed)",L51,K51) -> 0 | E51: =C51-D51 -> 0 | F51: =IF(C51=0,IF(D51=0,0,-1),(C51-D51)/C51) -> 0 | G51: Medium | H51: Variable | K51: =SUMIFS('Manual Actuals'!$C$2:$C$861,'Manual Actuals'!$D$2:$D$861,$A51,'Manual Actuals'!$E$2:$E$861,$B51,'Manual Actuals'!$H$2:$H$861,Setup!$B$4,'Manual Actuals'!$G$2:$G$861,"Yes") -> 0 | L51: =SUMIFS(bk_download!$L$2:$L$1902,bk_download!$H$2:$H$1902,$A51,bk_download!$I$2:$I$1902,$B51,bk_download!$K$2:$K$1902,Setup!$B$4,bk_download!$J$2:$J$1902,"Yes") -> 0 | M51: =K51-L51 -> 0
A52: Miscellaneous | B52: Cash/ATM | C52: 400 | D52: =IF(Setup!$B$8="Bank (Closed)",L52,K52) -> 202.95 | E52: =C52-D52 -> 197.05 | F52: =IF(C52=0,IF(D52=0,0,-1),(C52-D52)/C52) -> 0.492625 | G52: Medium | H52: Variable | K52: =SUMIFS('Manual Actuals'!$C$2:$C$861,'Manual Actuals'!$D$2:$D$861,$A52,'Manual Actuals'!$E$2:$E$861,$B52,'Manual Actuals'!$H$2:$H$861,Setup!$B$4,'Manual Actuals'!$G$2:$G$861,"Yes") -> 202.95 | L52: =SUMIFS(bk_download!$L$2:$L$1902,bk_download!$H$2:$H$1902,$A52,bk_download!$I$2:$I$1902,$B52,bk_download!$K$2:$K$1902,Setup!$B$4,bk_download!$J$2:$J$1902,"Yes") -> 0 | M52: =K52-L52 -> 202.95
A53: Miscellaneous | B53: General Merchandise | C53: 500 | D53: =IF(Setup!$B$8="Bank (Closed)",L53,K53) -> 0 | E53: =C53-D53 -> 500 | F53: =IF(C53=0,IF(D53=0,0,-1),(C53-D53)/C53) -> 1 | G53: Medium | H53: Variable | K53: =SUMIFS('Manual Actuals'!$C$2:$C$861,'Manual Actuals'!$D$2:$D$861,$A53,'Manual Actuals'!$E$2:$E$861,$B53,'Manual Actuals'!$H$2:$H$861,Setup!$B$4,'Manual Actuals'!$G$2:$G$861,"Yes") -> 0 | L53: =SUMIFS(bk_download!$L$2:$L$1902,bk_download!$H$2:$H$1902,$A53,bk_download!$I$2:$I$1902,$B53,bk_download!$K$2:$K$1902,Setup!$B$4,bk_download!$J$2:$J$1902,"Yes") -> 0 | M53: =K53-L53 -> 0
A54: Miscellaneous | B54: Other | C54: 900 | D54: =IF(Setup!$B$8="Bank (Closed)",L54,K54) -> 718.8 | E54: =C54-D54 -> 181.2 | F54: =IF(C54=0,IF(D54=0,0,-1),(C54-D54)/C54) -> 0.20133333 | G54: Medium | H54: Variable | K54: =SUMIFS('Manual Actuals'!$C$2:$C$861,'Manual Actuals'!$D$2:$D$861,$A54,'Manual Actuals'!$E$2:$E$861,$B54,'Manual Actuals'!$H$2:$H$861,Setup!$B$4,'Manual Actuals'!$G$2:$G$861,"Yes") -> 718.8 | L54: =SUMIFS(bk_download!$L$2:$L$1902,bk_download!$H$2:$H$1902,$A54,bk_download!$I$2:$I$1902,$B54,bk_download!$K$2:$K$1902,Setup!$B$4,bk_download!$J$2:$J$1902,"Yes") -> 0 | M54: =K54-L54 -> 718.8
A55: Miscellaneous | B55: Uncategorized | C55: 1000 | D55: =IF(Setup!$B$8="Bank (Closed)",L55,K55) -> 0 | E55: =C55-D55 -> 1000 | F55: =IF(C55=0,IF(D55=0,0,-1),(C55-D55)/C55) -> 1 | G55: Medium | H55: Variable | K55: =SUMIFS('Manual Actuals'!$C$2:$C$861,'Manual Actuals'!$D$2:$D$861,$A55,'Manual Actuals'!$E$2:$E$861,$B55,'Manual Actuals'!$H$2:$H$861,Setup!$B$4,'Manual Actuals'!$G$2:$G$861,"Yes") -> 0 | L55: =SUMIFS(bk_download!$L$2:$L$1902,bk_download!$H$2:$H$1902,$A55,bk_download!$I$2:$I$1902,$B55,bk_download!$K$2:$K$1902,Setup!$B$4,bk_download!$J$2:$J$1902,"Yes") -> 0 | M55: =K55-L55 -> 0
D56: =IF(Setup!$B$8="Bank (Closed)",L56,K56) -> 0 | K56: =SUMIFS('Manual Actuals'!$C$2:$C$861,'Manual Actuals'!$D$2:$D$861,$A56,'Manual Actuals'!$E$2:$E$861,$B56,'Manual Actuals'!$H$2:$H$861,Setup!$B$4,'Manual Actuals'!$G$2:$G$861,"Yes") -> 0 | L56: =SUMIFS(bk_download!$L$2:$L$1902,bk_download!$H$2:$H$1902,$A56,bk_download!$I$2:$I$1902,$B56,bk_download!$K$2:$K$1902,Setup!$B$4,bk_download!$J$2:$J$1902,"Yes") -> 0 | M56: =K56-L56 -> 0
A57: TOTAL MONTHLY EXPENSES | C57: =SUM(C4:C55) -> 15915.13 | D57: =IF(Setup!$B$8="Bank (Closed)",L57,K57) -> 0 | E57: =C57-D57 -> 15915.13 | F57: =IF(C57=0,0,E57/C57) -> 1 | K57: =SUMIFS('Manual Actuals'!$C$2:$C$861,'Manual Actuals'!$D$2:$D$861,$A57,'Manual Actuals'!$E$2:$E$861,$B57,'Manual Actuals'!$H$2:$H$861,Setup!$B$4,'Manual Actuals'!$G$2:$G$861,"Yes") -> 0 | L57: =SUMIFS(bk_download!$M$2:$M$1902,bk_download!$I$2:$I$1902,$A57,bk_download!$J$2:$J$1902,$B57,bk_download!$L$2:$L$1902,Setup!$B$4,bk_download!$K$2:$K$1902,"Yes") -> 0 | M57: =K57-L57 -> 0

Sheet Manual Actuals
A1: Date | B1: Description | C1: Actual Amount ($) | D1: Budget Category | E1: Subcategory | F1: Account | G1: Include? | H1: Month | I1: Notes
A2: 46232 | B2: City of Killeen | C2: 121 | D2: Utilities | E2: Water/Sewer/Trash | F2: Checking | G2: Yes | H2: =IF(A2="","",IF(A2>=46232,TEXT(DATE(YEAR(A2),MONTH(A2)+1,1),"mmmm yyyy"),TEXT(DATE(YEAR(A2),MONTH(A2),1),"mmmm yyyy"))) -> August 2026
A3: 46233 | B3: Google YouTube | C3: 82.89 | D3: Subscriptions | E3: Streaming | F3: Checking | G3: Yes | H3: =IF(A3="","",IF(A3>=46232,TEXT(DATE(YEAR(A3),MONTH(A3)+1,1),"mmmm yyyy"),TEXT(DATE(YEAR(A3),MONTH(A3),1),"mmmm yyyy"))) -> August 2026
A4: 46232 | B4: Camden Food Gates | C4: 16.5 | D4: Food | E4: Dining Out | F4: Checking | G4: Yes | H4: =IF(A4="","",IF(A4>=46232,TEXT(DATE(YEAR(A4),MONTH(A4)+1,1),"mmmm yyyy"),TEXT(DATE(YEAR(A4),MONTH(A4),1),"mmmm yyyy"))) -> August 2026
A5: 46232 | B5: Dunkin donuts | C5: 3.97 | D5: Food | E5: Dining Out | F5: Checking | G5: Yes | H5: =IF(A5="","",IF(A5>=46232,TEXT(DATE(YEAR(A5),MONTH(A5)+1,1),"mmmm yyyy"),TEXT(DATE(YEAR(A5),MONTH(A5),1),"mmmm yyyy"))) -> August 2026
A6: 46231 | B6: YouTube TV | C6: 29.99 | D6: Subscriptions | E6: Streaming | F6: Checking | G6: Yes | H6: =IF(A6="","",IF(A6>=46232,TEXT(DATE(YEAR(A6),MONTH(A6)+1,1),"mmmm yyyy"),TEXT(DATE(YEAR(A6),MONTH(A6),1),"mmmm yyyy"))) -> July 2026
A7: 46232 | B7: Star Mart | C7: 30 | D7: Vehicle | E7: Fuel | F7: Checking | G7: Yes | H7: =IF(A7="","",IF(A7>=46232,TEXT(DATE(YEAR(A7),MONTH(A7)+1,1),"mmmm yyyy"),TEXT(DATE(YEAR(A7),MONTH(A7),1),"mmmm yyyy"))) -> August 2026
A8: 46232 | B8: Amazon Delivery | C8: 75.04 | D8: Subscriptions | E8: Other Subscriptions | F8: Checking | G8: Yes | H8: =IF(A8="","",IF(A8>=46232,TEXT(DATE(YEAR(A8),MONTH(A8)+1,1),"mmmm yyyy"),TEXT(DATE(YEAR(A8),MONTH(A8),1),"mmmm yyyy"))) -> August 2026
A9: 46233 | B9: BOA Home Loan | C9: 406.91 | D9: Housing | E9: Mortgage/Rent | F9: Checking | G9: Yes | H9: =IF(A9="","",IF(A9>=46232,TEXT(DATE(YEAR(A9),MONTH(A9)+1,1),"mmmm yyyy"),TEXT(DATE(YEAR(A9),MONTH(A9),1),"mmmm yyyy"))) -> August 2026
A10: 46232 | B10: American home Shield | C10: 138.99 | D10: Housing | E10: Home Insurance | F10: Checking | G10: Yes | H10: =IF(A10="","",IF(A10>=46232,TEXT(DATE(YEAR(A10),MONTH(A10)+1,1),"mmmm yyyy"),TEXT(DATE(YEAR(A10),MONTH(A10),1),"mmmm yyyy"))) -> August 2026
A11: 46232 | B11: Star Mart | C11: 202.95 | D11: Miscellaneous | E11: Cash/ATM | F11: Checking | G11: Yes | H11: =IF(A11="","",IF(A11>=46232,TEXT(DATE(YEAR(A11),MONTH(A11)+1,1),"mmmm yyyy"),TEXT(DATE(YEAR(A11),MONTH(A11),1),"mmmm yyyy"))) -> August 2026
A12: 46233 | B12: Tommy Express | C12: 50.98 | D12: Subscriptions | E12: Other Subscriptions | F12: Checking | G12: Yes | H12: =IF(A12="","",IF(A12>=46232,TEXT(DATE(YEAR(A12),MONTH(A12)+1,1),"mmmm yyyy"),TEXT(DATE(YEAR(A12),MONTH(A12),1),"mmmm yyyy"))) -> August 2026
A13: 46233 | B13: Google YouTube premium | C13: 29.22 | D13: Subscriptions | E13: Streaming | F13: Checking | G13: Yes | H13: =IF(A13="","",IF(A13>=46232,TEXT(DATE(YEAR(A13),MONTH(A13)+1,1),"mmmm yyyy"),TEXT(DATE(YEAR(A13),MONTH(A13),1),"mmmm yyyy"))) -> August 2026
A14: 46232 | B14: Title Boxing | C14: 139.64 | D14: Subscriptions | E14: Other Subscriptions | F14: Checking | G14: Yes | H14: =IF(A14="","",IF(A14>=46232,TEXT(DATE(YEAR(A14),MONTH(A14)+1,1),"mmmm yyyy"),TEXT(DATE(YEAR(A14),MONTH(A14),1),"mmmm yyyy"))) -> August 2026
A15: 7/31/2026 | B15: Ford Motor Credit | C15: 1459.84 | D15: Vehicle | E15: Car Payment | F15: Checking | G15: Yes | H15: =IF(A15="","",IF(A15>=46232,TEXT(DATE(YEAR(A15),MONTH(A15)+1,1),"mmmm yyyy"),TEXT(DATE(YEAR(A15),MONTH(A15),1),"mmmm yyyy"))) -> August 2026
A16: 7/30/2026 | B16: Plane ticket | C16: 718.8 | D16: Miscellaneous | E16: Other | F16: Checking | G16: Yes | H16: =IF(A16="","",IF(A16>=46232,TEXT(DATE(YEAR(A16),MONTH(A16)+1,1),"mmmm yyyy"),TEXT(DATE(YEAR(A16),MONTH(A16),1),"mmmm yyyy"))) -> August 2026
A17: 7/29/2026 | B17: Klarna | C17: 216.34 | D17: Debt | E17: Loans | F17: Checking | G17: Yes | H17: =IF(A17="","",IF(A17>=46232,TEXT(DATE(YEAR(A17),MONTH(A17)+1,1),"mmmm yyyy"),TEXT(DATE(YEAR(A17),MONTH(A17),1),"mmmm yyyy"))) -> August 2026
A18: 7/29/2026 | B18: Klarna | C18: 17.02 | D18: Debt | E18: Loans | F18: Checking | G18: Yes | H18: =IF(A18="","",IF(A18>=46232,TEXT(DATE(YEAR(A18),MONTH(A18)+1,1),"mmmm yyyy"),TEXT(DATE(YEAR(A18),MONTH(A18),1),"mmmm yyyy"))) -> August 2026
A19: 7/29/2026 | B19: Affirm | C19: 33.45 | D19: Debt | E19: Loans | F19: Checking | G19: Yes | H19: =IF(A19="","",IF(A19>=46232,TEXT(DATE(YEAR(A19),MONTH(A19)+1,1),"mmmm yyyy"),TEXT(DATE(YEAR(A19),MONTH(A19),1),"mmmm yyyy"))) -> August 2026
A20: 7/30/2026 | B20: Affirm | C20: 22.31 | D20: Debt | E20: Loans | F20: Checking | G20: Yes | H20: =IF(A20="","",IF(A20>=46232,TEXT(DATE(YEAR(A20),MONTH(A20)+1,1),"mmmm yyyy"),TEXT(DATE(YEAR(A20),MONTH(A20),1),"mmmm yyyy"))) -> August 2026
H21: =IF(A21="","",IF(A21>=46232,TEXT(DATE(YEAR(A21),MONTH(A21)+1,1),"mmmm yyyy"),TEXT(DATE(YEAR(A21),MONTH(A21),1),"mmmm yyyy")))
H22: =IF(A22="","",IF(A22>=46232,TEXT(DATE(YEAR(A22),MONTH(A22)+1,1),"mmmm yyyy"),TEXT(DATE(YEAR(A22),MONTH(A22),1),"mmmm yyyy")))
H23: =IF(A23="","",IF(A23>=46232,TEXT(DATE(YEAR(A23),MONTH(A23)+1,1),"mmmm yyyy"),TEXT(DATE(YEAR(A23),MONTH(A23),1),"mmmm yyyy")))
H24: =IF(A24="","",IF(A24>=46232,TEXT(DATE(YEAR(A24),MONTH(A24)+1,1),"mmmm yyyy"),TEXT(DATE(YEAR(A24),MONTH(A24),1),"mmmm yyyy")))
H25: =IF(A25="","",IF(A25>=46232,TEXT(DATE(YEAR(A25),MONTH(A25)+1,1),"mmmm yyyy"),TEXT(DATE(YEAR(A25),MONTH(A25),1),"mmmm yyyy")))
H26: =IF(A26="","",IF(A26>=46232,TEXT(DATE(YEAR(A26),MONTH(A26)+1,1),"mmmm yyyy"),TEXT(DATE(YEAR(A26),MONTH(A26),1),"mmmm yyyy")))
H27: =IF(A27="","",IF(A27>=46232,TEXT(DATE(YEAR(A27),MONTH(A27)+1,1),"mmmm yyyy"),TEXT(DATE(YEAR(A27),MONTH(A27),1),"mmmm yyyy")))
H28: =IF(A28="","",IF(A28>=46232,TEXT(DATE(YEAR(A28),MONTH(A28)+1,1),"mmmm yyyy"),TEXT(DATE(YEAR(A28),MONTH(A28),1),"mmmm yyyy")))
H29: =IF(A29="","",IF(A29>=46232,TEXT(DATE(YEAR(A29),MONTH(A29)+1,1),"mmmm yyyy"),TEXT(DATE(YEAR(A29),MONTH(A29),1),"mmmm yyyy")))
H30: =IF(A30="","",IF(A30>=46232,TEXT(DATE(YEAR(A30),MONTH(A30)+1,1),"mmmm yyyy"),TEXT(DATE(YEAR(A30),MONTH(A30),1),"mmmm yyyy")))
H31: =IF(A31="","",IF(A31>=46232,TEXT(DATE(YEAR(A31),MONTH(A31)+1,1),"mmmm yyyy"),TEXT(DATE(YEAR(A31),MONTH(A31),1),"mmmm yyyy")))
H32: =IF(A32="","",IF(A32>=46232,TEXT(DATE(YEAR(A32),MONTH(A32)+1,1),"mmmm yyyy"),TEXT(DATE(YEAR(A32),MONTH(A32),1),"mmmm yyyy")))
... H861: =IF(A861="","",IF(A861>=46232,TEXT(DATE(YEAR(A861),MONTH(A861)+1,1),"mmmm yyyy"),TEXT(DATE(YEAR(A861),MONTH(A861),1),"mmmm yyyy")))

Sheet Monthly Summary
A1: MONTHLY CATEGORY SUMMARY
A3: Category | B3: Planned ($) | C3: Actual ($) | D3: Remaining ($) | E3: Variance % | F3: Share of Spend | G3: Status | H3: Trend Note
A4: Housing | B4: =SUMIF('Budget Plan'!$A$4:$A$55,A4,'Budget Plan'!$C$4:$C$55) -> 2669.78 | C4: =SUMIF('Budget Plan'!$A$4:$A$55,A4,'Budget Plan'!$D$4:$D$55) -> 545.9 | D4: =B4-C4 -> 2123.88 | E4: =IF(B4=0,IF(C4=0,0,-1),D4/B4) -> 0.79552622 | F4: =IF(SUM($C$4:$C$20)=0,0,C4/SUM($C$4:$C$20)) -> 0.14496063 | G4: =IF(C4=0,"No Activity",IF(D4<0,"Over Budget",IF(C4>B4*0.9,"Watch","On Track"))) -> On Track | H4: =IF(C4=0,"No bank expenses imported",IF(D4<0,"Reduce or reallocate "&TEXT(-D4,"$#,##0"),"Available "&TEXT(D4,"$#,##0"))) -> Available $2,124
A5: Utilities | B5: =SUMIF('Budget Plan'!$A$4:$A$55,A5,'Budget Plan'!$C$4:$C$55) -> 2149.88 | C5: =SUMIF('Budget Plan'!$A$4:$A$55,A5,'Budget Plan'!$D$4:$D$55) -> 121 | D5: =B5-C5 -> 2028.88 | E5: =IF(B5=0,IF(C5=0,0,-1),D5/B5) -> 0.94371779 | F5: =IF(SUM($C$4:$C$20)=0,0,C5/SUM($C$4:$C$20)) -> 0.03213086 | G5: =IF(C5=0,"No Activity",IF(D5<0,"Over Budget",IF(C5>B5*0.9,"Watch","On Track"))) -> On Track | H5: =IF(C5=0,"No bank expenses imported",IF(D5<0,"Reduce or reallocate "&TEXT(-D5,"$#,##0"),"Available "&TEXT(D5,"$#,##0"))) -> Available $2,029
A6: Vehicle | B6: =SUMIF('Budget Plan'!$A$4:$A$55,A6,'Budget Plan'!$C$4:$C$55) -> 2962.51 | C6: =SUMIF('Budget Plan'!$A$4:$A$55,A6,'Budget Plan'!$D$4:$D$55) -> 1489.84 | D6: =B6-C6 -> 1472.67 | E6: =IF(B6=0,IF(C6=0,0,-1),D6/B6) -> 0.49710212 | F6: =IF(SUM($C$4:$C$20)=0,0,C6/SUM($C$4:$C$20)) -> 0.39561852 | G6: =IF(C6=0,"No Activity",IF(D6<0,"Over Budget",IF(C6>B6*0.9,"Watch","On Track"))) -> On Track | H6: =IF(C6=0,"No bank expenses imported",IF(D6<0,"Reduce or reallocate "&TEXT(-D6,"$#,##0"),"Available "&TEXT(D6,"$#,##0"))) -> Available $1,473
A7: Food | B7: =SUMIF('Budget Plan'!$A$4:$A$55,A7,'Budget Plan'!$C$4:$C$55) -> 1300 | C7: =SUMIF('Budget Plan'!$A$4:$A$55,A7,'Budget Plan'!$D$4:$D$55) -> 20.47 | D7: =B7-C7 -> 1279.53 | E7: =IF(B7=0,IF(C7=0,0,-1),D7/B7) -> 0.98425385 | F7: =IF(SUM($C$4:$C$20)=0,0,C7/SUM($C$4:$C$20)) -> 0.0054356918 | G7: =IF(C7=0,"No Activity",IF(D7<0,"Over Budget",IF(C7>B7*0.9,"Watch","On Track"))) -> On Track | H7: =IF(C7=0,"No bank expenses imported",IF(D7<0,"Reduce or reallocate "&TEXT(-D7,"$#,##0"),"Available "&TEXT(D7,"$#,##0"))) -> Available $1,280
A8: Insurance | B8: =SUMIF('Budget Plan'!$A$4:$A$55,A8,'Budget Plan'!$C$4:$C$55) -> 0 | C8: =SUMIF('Budget Plan'!$A$4:$A$55,A8,'Budget Plan'!$D$4:$D$55) -> 0 | D8: =B8-C8 -> 0 | E8: =IF(B8=0,IF(C8=0,0,-1),D8/B8) -> 0 | F8: =IF(SUM($C$4:$C$20)=0,0,C8/SUM($C$4:$C$20)) -> 0 | G8: =IF(C8=0,"No Activity",IF(D8<0,"Over Budget",IF(C8>B8*0.9,"Watch","On Track"))) -> No Activity | H8: =IF(C8=0,"No bank expenses imported",IF(D8<0,"Reduce or reallocate "&TEXT(-D8,"$#,##0"),"Available "&TEXT(D8,"$#,##0"))) -> No bank expenses imported
A9: Medical | B9: =SUMIF('Budget Plan'!$A$4:$A$55,A9,'Budget Plan'!$C$4:$C$55) -> 53.07 | C9: =SUMIF('Budget Plan'!$A$4:$A$55,A9,'Budget Plan'!$D$4:$D$55) -> 0 | D9: =B9-C9 -> 53.07 | E9: =IF(B9=0,IF(C9=0,0,-1),D9/B9) -> 1 | F9: =IF(SUM($C$4:$C$20)=0,0,C9/SUM($C$4:$C$20)) -> 0 | G9: =IF(C9=0,"No Activity",IF(D9<0,"Over Budget",IF(C9>B9*0.9,"Watch","On Track"))) -> No Activity | H9: =IF(C9=0,"No bank expenses imported",IF(D9<0,"Reduce or reallocate "&TEXT(-D9,"$#,##0"),"Available "&TEXT(D9,"$#,##0"))) -> No bank expenses imported
A10: Children | B10: =SUMIF('Budget Plan'!$A$4:$A$55,A10,'Budget Plan'!$C$4:$C$55) -> 0 | C10: =SUMIF('Budget Plan'!$A$4:$A$55,A10,'Budget Plan'!$D$4:$D$55) -> 0 | D10: =B10-C10 -> 0 | E10: =IF(B10=0,IF(C10=0,0,-1),D10/B10) -> 0 | F10: =IF(SUM($C$4:$C$20)=0,0,C10/SUM($C$4:$C$20)) -> 0 | G10: =IF(C10=0,"No Activity",IF(D10<0,"Over Budget",IF(C10>B10*0.9,"Watch","On Track"))) -> No Activity | H10: =IF(C10=0,"No bank expenses imported",IF(D10<0,"Reduce or reallocate "&TEXT(-D10,"$#,##0"),"Available "&TEXT(D10,"$#,##0"))) -> No bank expenses imported
A11: Personal Care | B11: =SUMIF('Budget Plan'!$A$4:$A$55,A11,'Budget Plan'!$C$4:$C$55) -> 470 | C11: =SUMIF('Budget Plan'!$A$4:$A$55,A11,'Budget Plan'!$D$4:$D$55) -> 0 | D11: =B11-C11 -> 470 | E11: =IF(B11=0,IF(C11=0,0,-1),D11/B11) -> 1 | F11: =IF(SUM($C$4:$C$20)=0,0,C11/SUM($C$4:$C$20)) -> 0 | G11: =IF(C11=0,"No Activity",IF(D11<0,"Over Budget",IF(C11>B11*0.9,"Watch","On Track"))) -> No Activity | H11: =IF(C11=0,"No bank expenses imported",IF(D11<0,"Reduce or reallocate "&TEXT(-D11,"$#,##0"),"Available "&TEXT(D11,"$#,##0"))) -> No bank expenses imported
A12: Entertainment | B12: =SUMIF('Budget Plan'!$A$4:$A$55,A12,'Budget Plan'!$C$4:$C$55) -> 1000 | C12: =SUMIF('Budget Plan'!$A$4:$A$55,A12,'Budget Plan'!$D$4:$D$55) -> 0 | D12: =B12-C12 -> 1000 | E12: =IF(B12=0,IF(C12=0,0,-1),D12/B12) -> 1 | F12: =IF(SUM($C$4:$C$20)=0,0,C12/SUM($C$4:$C$20)) -> 0 | G12: =IF(C12=0,"No Activity",IF(D12<0,"Over Budget",IF(C12>B12*0.9,"Watch","On Track"))) -> No Activity | H12: =IF(C12=0,"No bank expenses imported",IF(D12<0,"Reduce or reallocate "&TEXT(-D12,"$#,##0"),"Available "&TEXT(D12,"$#,##0"))) -> No bank expenses imported
A13: Subscriptions | B13: =SUMIF('Budget Plan'!$A$4:$A$60,"Subscriptions",'Budget Plan'!$C$4:$C$60) -> 1600 | C13: =SUMIF('Budget Plan'!$A$4:$A$60,"Subscriptions",'Budget Plan'!$D$4:$D$60) -> 377.77 | D13: =B13-C13 -> 1222.23 | E13: =IF(B13=0,IF(C13=0,0,-1),(B13-C13)/B13) -> 0.76389375 | F13: =IF($C$20=0,0,C13/$C$20) -> 0.40983998 | G13: =IF(C13=0,"No Activity",IF(E13>=0.1,"On Track",IF(E13>=0,"Close","Over Budget"))) -> On Track | H13: =IF(C13=0,"No bank expenses imported","Available "&TEXT(D13,"$#,##0")) -> Available $1,222
A14: Giving | B14: =SUMIF('Budget Plan'!$A$4:$A$55,A14,'Budget Plan'!$C$4:$C$55) -> 0 | C14: =SUMIF('Budget Plan'!$A$4:$A$55,A14,'Budget Plan'!$D$4:$D$55) -> 0 | D14: =B14-C14 -> 0 | E14: =IF(B14=0,IF(C14=0,0,-1),D14/B14) -> 0 | F14: =IF(SUM($C$4:$C$20)=0,0,C14/SUM($C$4:$C$20)) -> 0 | G14: =IF(C14=0,"No Activity",IF(D14<0,"Over Budget",IF(C14>B14*0.9,"Watch","On Track"))) -> No Activity | H14: =IF(C14=0,"No bank expenses imported",IF(D14<0,"Reduce or reallocate "&TEXT(-D14,"$#,##0"),"Available "&TEXT(D14,"$#,##0"))) -> No bank expenses imported
A15: Pets | B15: =SUMIF('Budget Plan'!$A$4:$A$55,A15,'Budget Plan'!$C$4:$C$55) -> 200 | C15: =SUMIF('Budget Plan'!$A$4:$A$55,A15,'Budget Plan'!$D$4:$D$55) -> 0 | D15: =B15-C15 -> 200 | E15: =IF(B15=0,IF(C15=0,0,-1),D15/B15) -> 1 | F15: =IF(SUM($C$4:$C$20)=0,0,C15/SUM($C$4:$C$20)) -> 0 | G15: =IF(C15=0,"No Activity",IF(D15<0,"Over Budget",IF(C15>B15*0.9,"Watch","On Track"))) -> No Activity | H15: =IF(C15=0,"No bank expenses imported",IF(D15<0,"Reduce or reallocate "&TEXT(-D15,"$#,##0"),"Available "&TEXT(D15,"$#,##0"))) -> No bank expenses imported
A16: Debt | B16: =SUMIF('Budget Plan'!$A$4:$A$55,A16,'Budget Plan'!$C$4:$C$55) -> 619.89 | C16: =SUMIF('Budget Plan'!$A$4:$A$55,A16,'Budget Plan'!$D$4:$D$55) -> 289.12 | D16: =B16-C16 -> 330.77 | E16: =IF(B16=0,IF(C16=0,0,-1),D16/B16) -> 0.53359467 | F16: =IF(SUM($C$4:$C$20)=0,0,C16/SUM($C$4:$C$20)) -> 0.076774168 | G16: =IF(C16=0,"No Activity",IF(D16<0,"Over Budget",IF(C16>B16*0.9,"Watch","On Track"))) -> On Track | H16: =IF(C16=0,"No bank expenses imported",IF(D16<0,"Reduce or reallocate "&TEXT(-D16,"$#,##0"),"Available "&TEXT(D16,"$#,##0"))) -> Available $331
A17: Savings | B17: =SUMIF('Budget Plan'!$A$4:$A$55,A17,'Budget Plan'!$C$4:$C$55) -> 90 | C17: =SUMIF('Budget Plan'!$A$4:$A$55,A17,'Budget Plan'!$D$4:$D$55) -> 0 | D17: =B17-C17 -> 90 | E17: =IF(B17=0,IF(C17=0,0,-1),D17/B17) -> 1 | F17: =IF(SUM($C$4:$C$20)=0,0,C17/SUM($C$4:$C$20)) -> 0 | G17: =IF(C17=0,"No Activity",IF(D17<0,"Over Budget",IF(C17>B17*0.9,"Watch","On Track"))) -> No Activity | H17: =IF(C17=0,"No bank expenses imported",IF(D17<0,"Reduce or reallocate "&TEXT(-D17,"$#,##0"),"Available "&TEXT(D17,"$#,##0"))) -> No bank expenses imported
A18: Taxes | B18: =SUMIF('Budget Plan'!$A$4:$A$55,A18,'Budget Plan'!$C$4:$C$55) -> 0 | C18: =SUMIF('Budget Plan'!$A$4:$A$55,A18,'Budget Plan'!$D$4:$D$55) -> 0 | D18: =B18-C18 -> 0 | E18: =IF(B18=0,IF(C18=0,0,-1),D18/B18) -> 0 | F18: =IF(SUM($C$4:$C$20)=0,0,C18/SUM($C$4:$C$20)) -> 0 | G18: =IF(C18=0,"No Activity",IF(D18<0,"Over Budget",IF(C18>B18*0.9,"Watch","On Track"))) -> No Activity | H18: =IF(C18=0,"No bank expenses imported",IF(D18<0,"Reduce or reallocate "&TEXT(-D18,"$#,##0"),"Available "&TEXT(D18,"$#,##0"))) -> No bank expenses imported
A19: Legal | B19: =SUMIF('Budget Plan'!$A$4:$A$55,A19,'Budget Plan'!$C$4:$C$55) -> 0 | C19: =SUMIF('Budget Plan'!$A$4:$A$55,A19,'Budget Plan'!$D$4:$D$55) -> 0 | D19: =B19-C19 -> 0 | E19: =IF(B19=0,IF(C19=0,0,-1),D19/B19) -> 0 | F19: =IF(SUM($C$4:$C$20)=0,0,C19/SUM($C$4:$C$20)) -> 0 | G19: =IF(C19=0,"No Activity",IF(D19<0,"Over Budget",IF(C19>B19*0.9,"Watch","On Track"))) -> No Activity | H19: =IF(C19=0,"No bank expenses imported",IF(D19<0,"Reduce or reallocate "&TEXT(-D19,"$#,##0"),"Available "&TEXT(D19,"$#,##0"))) -> No bank expenses imported
A20: Miscellaneous | B20: =SUMIF('Budget Plan'!$A$4:$A$55,A20,'Budget Plan'!$C$4:$C$55) -> 2800 | C20: =SUMIF('Budget Plan'!$A$4:$A$55,A20,'Budget Plan'!$D$4:$D$55) -> 921.75 | D20: =B20-C20 -> 1878.25 | E20: =IF(B20=0,IF(C20=0,0,-1),D20/B20) -> 0.67080357 | F20: =IF(SUM($C$4:$C$20)=0,0,C20/SUM($C$4:$C$20)) -> 0.24476546 | G20: =IF(C20=0,"No Activity",IF(D20<0,"Over Budget",IF(C20>B20*0.9,"Watch","On Track"))) -> On Track | H20: =IF(C20=0,"No bank expenses imported",IF(D20<0,"Reduce or reallocate "&TEXT(-D20,"$#,##0"),"Available "&TEXT(D20,"$#,##0"))) -> Available $1,878

Sheet Goals
A1: SAVINGS GOALS & FEASIBILITY
A3: Goal | B3: Priority | C3: Target Amount ($) | D3: Current Saved ($) | E3: Target Date | F3: Months Remaining | G3: Required Monthly ($) | H3: Planned Monthly ($) | I3: Projected Completion | J3: Status | K3: Monthly Gap ($) | L3: Notes
A4: Emergency Fund | B4: Critical | F4: =IF(E4="","",MAX(0,DATEDIF(Setup!$B$4,E4,"m"))) | G4: =IF(OR(C4="",F4=""),0,MAX(0,(C4-D4)/MAX(1,F4))) -> 0 | I4: =IF(H4<=0,"",EDATE(Setup!$B$4,ROUNDUP(MAX(0,C4-D4)/H4,0))) | J4: =IF(C4="","",IF(D4>=C4,"Complete",IF(H4>=G4,"On Track",IF(H4>0,"Behind","Not Funded")))) | K4: =MAX(0,G4-H4) -> 0
A5: Savings | B5: High | C5: 10000 | D5: 76.16 | E5: 46600 | F5: =IF(E5="","",MAX(0,DATEDIF(Setup!$B$4,E5,"m"))) -> 12 | G5: 826.98667 | H5: 375 | I5: =IF(H5<=0,"",EDATE(Setup!$B$4,ROUNDUP(MAX(0,C5-D5)/H5,0))) -> 47058 | J5: Behind | K5: 451.98667
A6: Goal 3 | B6: Medium | F6: =IF(E6="","",MAX(0,DATEDIF(Setup!$B$4,E6,"m"))) | G6: 0 | I6: =IF(H6<=0,"",EDATE(Setup!$B$4,ROUNDUP(MAX(0,C6-D6)/H6,0))) | K6: 0
A7: Goal 4 | B7: Medium | F7: =IF(E7="","",MAX(0,DATEDIF(Setup!$B$4,E7,"m"))) | G7: 0 | I7: =IF(H7<=0,"",EDATE(Setup!$B$4,ROUNDUP(MAX(0,C7-D7)/H7,0))) | K7: 0
A8: Goal 5 | B8: Low | F8: =IF(E8="","",MAX(0,DATEDIF(Setup!$B$4,E8,"m"))) | G8: 0 | I8: =IF(H8<=0,"",EDATE(Setup!$B$4,ROUNDUP(MAX(0,C8-D8)/H8,0))) | K8: 0
A9: Goal 6 | B9: Low | F9: =IF(E9="","",MAX(0,DATEDIF(Setup!$B$4,E9,"m"))) | G9: 0 | I9: =IF(H9<=0,"",EDATE(Setup!$B$4,ROUNDUP(MAX(0,C9-D9)/H9,0))) | K9: 0

Sheet Debts
A1: DEBT PAYOFF & PAYMENT RECOMMENDATION
A3: Debt Name | B3: Type | C3: Current Balance ($) | D3: APR | E3: Minimum Payment ($) | F3: Due Day | G3: Promo End | H3: Strategy Rank | I3: Recommended Extra ($) | J3: Recommended Payment ($) | K3: Months to Payoff | L3: Projected Payoff | M3: Est. Interest ($) | N3: Notes
A4: Debt 1 | B4: Credit Card | H4: =IF(C4<=0,"",IF(Setup!$B$6="Avalanche",_xludf.RANK.EQ(D4,$D$4:$D$11,0),IF(Setup!$B$6="Snowball",_xludf.RANK.EQ(C4,$C$4:$C$11,1),_xludf.RANK.EQ(E4,$E$4:$E$11,0)))) | I4: =IF(H4=1,MAX(0,Dashboard!$B$10-Setup!$B$5),0) -> 0 | J4: =MIN(C4,E4+I4) -> 0 | K4: =IF(OR(C4<=0,J4<=0),"",IF(D4=0,ROUNDUP(C4/J4,0),ROUNDUP(NPER(D4/12,-J4,C4),0))) | L4: =IF(K4="","",EDATE(Setup!$B$4,K4)) | M4: =IF(K4="","",MAX(0,J4*K4-C4))
A5: Debt 2 | B5: Credit Card | H5: =IF(C5<=0,"",IF(Setup!$B$6="Avalanche",_xludf.RANK.EQ(D5,$D$4:$D$11,0),IF(Setup!$B$6="Snowball",_xludf.RANK.EQ(C5,$C$4:$C$11,1),_xludf.RANK.EQ(E5,$E$4:$E$11,0)))) | I5: =IF(H5=1,MAX(0,Dashboard!$B$10-Setup!$B$5),0) -> 0 | J5: 0 | L5: =IF(K5="","",EDATE(Setup!$B$4,K5))
A6: Debt 3 | B6: Loan | H6: =IF(C6<=0,"",IF(Setup!$B$6="Avalanche",_xludf.RANK.EQ(D6,$D$4:$D$11,0),IF(Setup!$B$6="Snowball",_xludf.RANK.EQ(C6,$C$4:$C$11,1),_xludf.RANK.EQ(E6,$E$4:$E$11,0)))) | I6: =IF(H6=1,MAX(0,Dashboard!$B$10-Setup!$B$5),0) -> 0 | J6: 0 | L6: =IF(K6="","",EDATE(Setup!$B$4,K6))
A7: Debt 4 | B7: Loan | H7: =IF(C7<=0,"",IF(Setup!$B$6="Avalanche",_xludf.RANK.EQ(D7,$D$4:$D$11,0),IF(Setup!$B$6="Snowball",_xludf.RANK.EQ(C7,$C$4:$C$11,1),_xludf.RANK.EQ(E7,$E$4:$E$11,0)))) | I7: =IF(H7=1,MAX(0,Dashboard!$B$10-Setup!$B$5),0) -> 0 | J7: 0 | L7: =IF(K7="","",EDATE(Setup!$B$4,K7))
A8: Debt 5 | B8: Vehicle | H8: =IF(C8<=0,"",IF(Setup!$B$6="Avalanche",_xludf.RANK.EQ(D8,$D$4:$D$11,0),IF(Setup!$B$6="Snowball",_xludf.RANK.EQ(C8,$C$4:$C$11,1),_xludf.RANK.EQ(E8,$E$4:$E$11,0)))) | I8: =IF(H8=1,MAX(0,Dashboard!$B$10-Setup!$B$5),0) -> 0 | J8: 0 | L8: =IF(K8="","",EDATE(Setup!$B$4,K8))
A9: Debt 6 | B9: Medical | H9: =IF(C9<=0,"",IF(Setup!$B$6="Avalanche",_xludf.RANK.EQ(D9,$D$4:$D$11,0),IF(Setup!$B$6="Snowball",_xludf.RANK.EQ(C9,$C$4:$C$11,1),_xludf.RANK.EQ(E9,$E$4:$E$11,0)))) | I9: =IF(H9=1,MAX(0,Dashboard!$B$10-Setup!$B$5),0) -> 0 | J9: 0 | L9: =IF(K9="","",EDATE(Setup!$B$4,K9))
A10: Debt 7 | B10: Other | H10: =IF(C10<=0,"",IF(Setup!$B$6="Avalanche",_xludf.RANK.EQ(D10,$D$4:$D$11,0),IF(Setup!$B$6="Snowball",_xludf.RANK.EQ(C10,$C$4:$C$11,1),_xludf.RANK.EQ(E10,$E$4:$E$11,0)))) | I10: =IF(H10=1,MAX(0,Dashboard!$B$10-Setup!$B$5),0) -> 0 | J10: 0 | L10: =IF(K10="","",EDATE(Setup!$B$4,K10))
A11: Debt 8 | B11: Other | H11: =IF(C11<=0,"",IF(Setup!$B$6="Avalanche",_xludf.RANK.EQ(D11,$D$4:$D$11,0),IF(Setup!$B$6="Snowball",_xludf.RANK.EQ(C11,$C$4:$C$11,1),_xludf.RANK.EQ(E11,$E$4:$E$11,0)))) | I11: =IF(H11=1,MAX(0,Dashboard!$B$10-Setup!$B$5),0) -> 0 | J11: 0 | L11: =IF(K11="","",EDATE(Setup!$B$4,K11))
A13: Debt Summary | B13: Value
A14: Total Debt | B14: =SUM(C4:C11) -> 0
A15: Total Minimum Payments | B15: =SUM(E4:E11) -> 0

Sheet Reconciliation
A1: MONTH-END BANK RECONCILIATION
A3: Category | B3: Manual Actual ($) | C3: Bank Actual ($) | D3: Difference ($) | E3: Difference % | F3: Status | G3: Action
A4: Housing | B4: =SUMIFS('Manual Actuals'!$C$2:$C$861,'Manual Actuals'!$D$2:$D$861,$A4,'Manual Actuals'!$H$2:$H$861,Setup!$B$4,'Manual Actuals'!$G$2:$G$861,"Yes") -> 545.9 | C4: =SUMIFS(bk_download!$L$2:$L$1902,bk_download!$H$2:$H$1902,$A4,bk_download!$K$2:$K$1902,Setup!$B$4,bk_download!$J$2:$J$1902,"Yes") -> 0 | D4: =B4-C4 -> 545.9 | E4: =IF(C4=0,IF(B4=0,0,1),D4/C4) -> 1 | F4: =IF(ABS(D4)<=1,"Matched",IF(ABS(D4)<=10,"Review","Investigate")) -> Investigate | G4: =IF(F4="Matched","None",IF(D4>0,"Manual exceeds bank","Bank exceeds manual")) -> Manual exceeds bank
A5: Utilities | B5: =SUMIFS('Manual Actuals'!$C$2:$C$861,'Manual Actuals'!$D$2:$D$861,$A5,'Manual Actuals'!$H$2:$H$861,Setup!$B$4,'Manual Actuals'!$G$2:$G$861,"Yes") -> 121 | C5: =SUMIFS(bk_download!$L$2:$L$1902,bk_download!$H$2:$H$1902,$A5,bk_download!$K$2:$K$1902,Setup!$B$4,bk_download!$J$2:$J$1902,"Yes") -> 0 | D5: =B5-C5 -> 121 | E5: =IF(C5=0,IF(B5=0,0,1),D5/C5) -> 1 | F5: =IF(ABS(D5)<=1,"Matched",IF(ABS(D5)<=10,"Review","Investigate")) -> Investigate | G5: =IF(F5="Matched","None",IF(D5>0,"Manual exceeds bank","Bank exceeds manual")) -> Manual exceeds bank
A6: Vehicle | B6: =SUMIFS('Manual Actuals'!$C$2:$C$861,'Manual Actuals'!$D$2:$D$861,$A6,'Manual Actuals'!$H$2:$H$861,Setup!$B$4,'Manual Actuals'!$G$2:$G$861,"Yes") -> 1489.84 | C6: =SUMIFS(bk_download!$L$2:$L$1902,bk_download!$H$2:$H$1902,$A6,bk_download!$K$2:$K$1902,Setup!$B$4,bk_download!$J$2:$J$1902,"Yes") -> 3.97 | D6: =B6-C6 -> 1485.87 | E6: =IF(C6=0,IF(B6=0,0,1),D6/C6) -> 374.27456 | F6: =IF(ABS(D6)<=1,"Matched",IF(ABS(D6)<=10,"Review","Investigate")) -> Investigate | G6: =IF(F6="Matched","None",IF(D6>0,"Manual exceeds bank","Bank exceeds manual")) -> Manual exceeds bank
A7: Food | B7: =SUMIFS('Manual Actuals'!$C$2:$C$861,'Manual Actuals'!$D$2:$D$861,$A7,'Manual Actuals'!$H$2:$H$861,Setup!$B$4,'Manual Actuals'!$G$2:$G$861,"Yes") -> 20.47 | C7: =SUMIFS(bk_download!$L$2:$L$1902,bk_download!$H$2:$H$1902,$A7,bk_download!$K$2:$K$1902,Setup!$B$4,bk_download!$J$2:$J$1902,"Yes") -> 0 | D7: =B7-C7 -> 20.47 | E7: =IF(C7=0,IF(B7=0,0,1),D7/C7) -> 1 | F7: =IF(ABS(D7)<=1,"Matched",IF(ABS(D7)<=10,"Review","Investigate")) -> Investigate | G7: =IF(F7="Matched","None",IF(D7>0,"Manual exceeds bank","Bank exceeds manual")) -> Manual exceeds bank
A8: Insurance | B8: =SUMIFS('Manual Actuals'!$C$2:$C$861,'Manual Actuals'!$D$2:$D$861,$A8,'Manual Actuals'!$H$2:$H$861,Setup!$B$4,'Manual Actuals'!$G$2:$G$861,"Yes") -> 0 | C8: =SUMIFS(bk_download!$L$2:$L$1902,bk_download!$H$2:$H$1902,$A8,bk_download!$K$2:$K$1902,Setup!$B$4,bk_download!$J$2:$J$1902,"Yes") -> 0 | D8: =B8-C8 -> 0 | E8: =IF(C8=0,IF(B8=0,0,1),D8/C8) -> 0 | F8: =IF(ABS(D8)<=1,"Matched",IF(ABS(D8)<=10,"Review","Investigate")) -> Matched | G8: =IF(F8="Matched","None",IF(D8>0,"Manual exceeds bank","Bank exceeds manual")) -> None
A9: Medical | B9: =SUMIFS('Manual Actuals'!$C$2:$C$861,'Manual Actuals'!$D$2:$D$861,$A9,'Manual Actuals'!$H$2:$H$861,Setup!$B$4,'Manual Actuals'!$G$2:$G$861,"Yes") -> 0 | C9: =SUMIFS(bk_download!$L$2:$L$1902,bk_download!$H$2:$H$1902,$A9,bk_download!$K$2:$K$1902,Setup!$B$4,bk_download!$J$2:$J$1902,"Yes") -> 0 | D9: =B9-C9 -> 0 | E9: =IF(C9=0,IF(B9=0,0,1),D9/C9) -> 0 | F9: =IF(ABS(D9)<=1,"Matched",IF(ABS(D9)<=10,"Review","Investigate")) -> Matched | G9: =IF(F9="Matched","None",IF(D9>0,"Manual exceeds bank","Bank exceeds manual")) -> None
A10: Children | B10: =SUMIFS('Manual Actuals'!$C$2:$C$861,'Manual Actuals'!$D$2:$D$861,$A10,'Manual Actuals'!$H$2:$H$861,Setup!$B$4,'Manual Actuals'!$G$2:$G$861,"Yes") -> 0 | C10: =SUMIFS(bk_download!$L$2:$L$1902,bk_download!$H$2:$H$1902,$A10,bk_download!$K$2:$K$1902,Setup!$B$4,bk_download!$J$2:$J$1902,"Yes") -> 0 | D10: =B10-C10 -> 0 | E10: =IF(C10=0,IF(B10=0,0,1),D10/C10) -> 0 | F10: =IF(ABS(D10)<=1,"Matched",IF(ABS(D10)<=10,"Review","Investigate")) -> Matched | G10: =IF(F10="Matched","None",IF(D10>0,"Manual exceeds bank","Bank exceeds manual")) -> None
A11: Personal Care | B11: =SUMIFS('Manual Actuals'!$C$2:$C$861,'Manual Actuals'!$D$2:$D$861,$A11,'Manual Actuals'!$H$2:$H$861,Setup!$B$4,'Manual Actuals'!$G$2:$G$861,"Yes") -> 0 | C11: =SUMIFS(bk_download!$L$2:$L$1902,bk_download!$H$2:$H$1902,$A11,bk_download!$K$2:$K$1902,Setup!$B$4,bk_download!$J$2:$J$1902,"Yes") -> 16.5 | D11: =B11-C11 -> -16.5 | E11: =IF(C11=0,IF(B11=0,0,1),D11/C11) -> -1 | F11: =IF(ABS(D11)<=1,"Matched",IF(ABS(D11)<=10,"Review","Investigate")) -> Investigate | G11: =IF(F11="Matched","None",IF(D11>0,"Manual exceeds bank","Bank exceeds manual")) -> Bank exceeds manual
A12: Entertainment | B12: =SUMIFS('Manual Actuals'!$C$2:$C$861,'Manual Actuals'!$D$2:$D$861,$A12,'Manual Actuals'!$H$2:$H$861,Setup!$B$4,'Manual Actuals'!$G$2:$G$861,"Yes") -> 0 | C12: =SUMIFS(bk_download!$L$2:$L$1902,bk_download!$H$2:$H$1902,$A12,bk_download!$K$2:$K$1902,Setup!$B$4,bk_download!$J$2:$J$1902,"Yes") -> 0 | D12: =B12-C12 -> 0 | E12: =IF(C12=0,IF(B12=0,0,1),D12/C12) -> 0 | F12: =IF(ABS(D12)<=1,"Matched",IF(ABS(D12)<=10,"Review","Investigate")) -> Matched | G12: =IF(F12="Matched","None",IF(D12>0,"Manual exceeds bank","Bank exceeds manual")) -> None
A13: Giving | B13: =SUMIFS('Manual Actuals'!$C$2:$C$861,'Manual Actuals'!$D$2:$D$861,$A13,'Manual Actuals'!$H$2:$H$861,Setup!$B$4,'Manual Actuals'!$G$2:$G$861,"Yes") -> 0 | C13: =SUMIFS(bk_download!$L$2:$L$1902,bk_download!$H$2:$H$1902,$A13,bk_download!$K$2:$K$1902,Setup!$B$4,bk_download!$J$2:$J$1902,"Yes") -> 0 | D13: =B13-C13 -> 0 | E13: =IF(C13=0,IF(B13=0,0,1),D13/C13) -> 0 | F13: =IF(ABS(D13)<=1,"Matched",IF(ABS(D13)<=10,"Review","Investigate")) -> Matched | G13: =IF(F13="Matched","None",IF(D13>0,"Manual exceeds bank","Bank exceeds manual")) -> None
A14: Subscriptions | B14: =SUMIF('Budget Plan'!$A$4:$A$60,"Subscriptions",'Budget Plan'!$K$4:$K$60) -> 377.77 | C14: =SUMIFS(bk_download!$L$2:$L$1902,bk_download!$H$2:$H$1902,$A14,bk_download!$K$2:$K$1902,Setup!$B$4,bk_download!$J$2:$J$1902,"Yes") -> 203.99 | D14: =B14-C14 -> 173.78 | E14: =IF(B14=0,IF(C14=0,0,1),ABS(D14)/B14) -> 0.46001535 | F14: =IF(D14=0,"Matched",IF(ABS(E14)<=0.05,"Close","Investigate")) -> Investigate | G14: =IF(F14="Matched","None",IF(D14>0,"Manual exceeds bank","Bank exceeds manual")) -> Manual exceeds bank
A15: Pets | B15: =SUMIFS('Manual Actuals'!$C$2:$C$861,'Manual Actuals'!$D$2:$D$861,$A15,'Manual Actuals'!$H$2:$H$861,Setup!$B$4,'Manual Actuals'!$G$2:$G$861,"Yes") -> 0 | C15: =SUMIFS(bk_download!$L$2:$L$1902,bk_download!$H$2:$H$1902,$A15,bk_download!$K$2:$K$1902,Setup!$B$4,bk_download!$J$2:$J$1902,"Yes") -> 0 | D15: =B15-C15 -> 0 | E15: =IF(C15=0,IF(B15=0,0,1),D15/C15) -> 0 | F15: =IF(ABS(D15)<=1,"Matched",IF(ABS(D15)<=10,"Review","Investigate")) -> Matched | G15: =IF(F15="Matched","None",IF(D15>0,"Manual exceeds bank","Bank exceeds manual")) -> None
A16: Debt | B16: =SUMIFS('Manual Actuals'!$C$2:$C$861,'Manual Actuals'!$D$2:$D$861,$A16,'Manual Actuals'!$H$2:$H$861,Setup!$B$4,'Manual Actuals'!$G$2:$G$861,"Yes") -> 289.12 | C16: =SUMIFS(bk_download!$L$2:$L$1902,bk_download!$H$2:$H$1902,$A16,bk_download!$K$2:$K$1902,Setup!$B$4,bk_download!$J$2:$J$1902,"Yes") -> 0 | D16: =B16-C16 -> 289.12 | E16: =IF(C16=0,IF(B16=0,0,1),D16/C16) -> 1 | F16: =IF(ABS(D16)<=1,"Matched",IF(ABS(D16)<=10,"Review","Investigate")) -> Investigate | G16: =IF(F16="Matched","None",IF(D16>0,"Manual exceeds bank","Bank exceeds manual")) -> Manual exceeds bank
A17: Savings | B17: =SUMIFS('Manual Actuals'!$C$2:$C$861,'Manual Actuals'!$D$2:$D$861,$A17,'Manual Actuals'!$H$2:$H$861,Setup!$B$4,'Manual Actuals'!$G$2:$G$861,"Yes") -> 0 | C17: =SUMIFS(bk_download!$L$2:$L$1902,bk_download!$H$2:$H$1902,$A17,bk_download!$K$2:$K$1902,Setup!$B$4,bk_download!$J$2:$J$1902,"Yes") -> 0 | D17: =B17-C17 -> 0 | E17: =IF(C17=0,IF(B17=0,0,1),D17/C17) -> 0 | F17: =IF(ABS(D17)<=1,"Matched",IF(ABS(D17)<=10,"Review","Investigate")) -> Matched | G17: =IF(F17="Matched","None",IF(D17>0,"Manual exceeds bank","Bank exceeds manual")) -> None
A18: Taxes | B18: =SUMIFS('Manual Actuals'!$C$2:$C$861,'Manual Actuals'!$D$2:$D$861,$A18,'Manual Actuals'!$H$2:$H$861,Setup!$B$4,'Manual Actuals'!$G$2:$G$861,"Yes") -> 0 | C18: =SUMIFS(bk_download!$L$2:$L$1902,bk_download!$H$2:$H$1902,$A18,bk_download!$K$2:$K$1902,Setup!$B$4,bk_download!$J$2:$J$1902,"Yes") -> 0 | D18: =B18-C18 -> 0 | E18: =IF(C18=0,IF(B18=0,0,1),D18/C18) -> 0 | F18: =IF(ABS(D18)<=1,"Matched",IF(ABS(D18)<=10,"Review","Investigate")) -> Matched | G18: =IF(F18="Matched","None",IF(D18>0,"Manual exceeds bank","Bank exceeds manual")) -> None
A19: Legal | B19: =SUMIFS('Manual Actuals'!$C$2:$C$861,'Manual Actuals'!$D$2:$D$861,$A19,'Manual Actuals'!$H$2:$H$861,Setup!$B$4,'Manual Actuals'!$G$2:$G$861,"Yes") -> 0 | C19: =SUMIFS(bk_download!$L$2:$L$1902,bk_download!$H$2:$H$1902,$A19,bk_download!$K$2:$K$1902,Setup!$B$4,bk_download!$J$2:$J$1902,"Yes") -> 0 | D19: =B19-C19 -> 0 | E19: =IF(C19=0,IF(B19=0,0,1),D19/C19) -> 0 | F19: =IF(ABS(D19)<=1,"Matched",IF(ABS(D19)<=10,"Review","Investigate")) -> Matched | G19: =IF(F19="Matched","None",IF(D19>0,"Manual exceeds bank","Bank exceeds manual")) -> None
A20: Miscellaneous | B20: =SUMIFS('Manual Actuals'!$C$2:$C$861,'Manual Actuals'!$D$2:$D$861,$A20,'Manual Actuals'!$H$2:$H$861,Setup!$B$4,'Manual Actuals'!$G$2:$G$861,"Yes") -> 921.75 | C20: =SUMIFS(bk_download!$L$2:$L$1902,bk_download!$H$2:$H$1902,$A20,bk_download!$K$2:$K$1902,Setup!$B$4,bk_download!$J$2:$J$1902,"Yes") -> 0 | D20: =B20-C20 -> 921.75 | E20: =IF(C20=0,IF(B20=0,0,1),D20/C20) -> 1 | F20: =IF(ABS(D20)<=1,"Matched",IF(ABS(D20)<=10,"Review","Investigate")) -> Investigate | G20: =IF(F20="Matched","None",IF(D20>0,"Manual exceeds bank","Bank exceeds manual")) -> Manual exceeds bank
A21: TOTAL | B21: =SUM(B4:B20) -> 3765.85 | C21: =SUM(C4:C20) -> 224.46 | D21: =B21-C21 -> 3541.39 | E21: =IF(C21=0,IF(B21=0,0,1),D21/C21) -> 15.777377 | F21: =IF(ABS(D21)<=1,"Matched","Review") -> Review

Sheet bk_download
A1: Date | B1: Description | C1: Original Description | D1: Category | E1: Amount | F1: Status | G1: Account | H1: Budget Category | I1: Subcategory | J1: Include? | K1: Month | L1: Expense Amount ($) | M1: Income Amount ($) | N1: Review Note
A2: 46241 | B2: Mariner Finance 080726 | C2: Mariner Finance 080726 | D2: Category Pending | E2: -101.8 | F2: Pending | G2: =IF(A2="","","Checking") -> Checking | H2: Miscellaneous | I2: Uncategorized | J2: =IF(A2="","",IF(OR(H2="Transfers",H2="Income",D2="Transfer",D2="Category Pending"),"No","Yes")) -> No | K2: =IF(A2="","",IF(A2>=46232,TEXT(DATE(YEAR(A2),MONTH(A2)+1,1),"mmmm yyyy"),TEXT(DATE(YEAR(A2),MONTH(A2),1),"mmmm yyyy"))) -> September 2026 | L2: =IF(AND(J2="Yes",E2<0),-E2,0) -> 0 | M2: =IF(AND(J2="Yes",E2>0),E2,0) -> 0 | N2: =IF(A2="","",IF(D2="Category Pending","Needs categorization",IF(COUNTIFS($A$2:A2,A2,$B$2:B2,B2,$E$2:E2,E2)>1,"Possible duplicate",""))) -> Needs categorization
A3: 46241 | B3: CASEYS #4775 080726 | C3: CASEYS #4775 080726 | D3: Category Pending | E3: -6.25 | F3: Pending | G3: =IF(A3="","","Checking") -> Checking | H3: Miscellaneous | I3: Uncategorized | J3: =IF(A3="","",IF(OR(H3="Transfers",H3="Income",D3="Transfer",D3="Category Pending"),"No","Yes")) -> No | K3: =IF(A3="","",IF(A3>=46232,TEXT(DATE(YEAR(A3),MONTH(A3)+1,1),"mmmm yyyy"),TEXT(DATE(YEAR(A3),MONTH(A3),1),"mmmm yyyy"))) -> September 2026 | L3: =IF(AND(J3="Yes",E3<0),-E3,0) -> 0 | M3: =IF(AND(J3="Yes",E3>0),E3,0) -> 0 | N3: =IF(A3="","",IF(D3="Category Pending","Needs categorization",IF(COUNTIFS($A$2:A3,A3,$B$2:B3,B3,$E$2:E3,E3)>1,"Possible duplicate",""))) -> Needs categorization
A4: 46240 | B4: DD *DOORDASH WABAH 080626 | C4: DD *DOORDASH WABAH 080626 | D4: Category Pending | E4: -80.55 | F4: Pending | G4: =IF(A4="","","Checking") -> Checking | H4: Miscellaneous | I4: Uncategorized | J4: =IF(A4="","",IF(OR(H4="Transfers",H4="Income",D4="Transfer",D4="Category Pending"),"No","Yes")) -> No | K4: =IF(A4="","",IF(A4>=46232,TEXT(DATE(YEAR(A4),MONTH(A4)+1,1),"mmmm yyyy"),TEXT(DATE(YEAR(A4),MONTH(A4),1),"mmmm yyyy"))) -> September 2026 | L4: =IF(AND(J4="Yes",E4<0),-E4,0) -> 0 | M4: =IF(AND(J4="Yes",E4>0),E4,0) -> 0 | N4: =IF(A4="","",IF(D4="Category Pending","Needs categorization",IF(COUNTIFS($A$2:A4,A4,$B$2:B4,B4,$E$2:E4,E4)>1,"Possible duplicate",""))) -> Needs categorization
A5: 46241 | B5: MOLLY MAID OF GREATE 080726 | C5: MOLLY MAID OF GREATE 080726 | D5: Category Pending | E5: -250 | F5: Pending | G5: =IF(A5="","","Checking") -> Checking | H5: Miscellaneous | I5: Uncategorized | J5: =IF(A5="","",IF(OR(H5="Transfers",H5="Income",D5="Transfer",D5="Category Pending"),"No","Yes")) -> No | K5: =IF(A5="","",IF(A5>=46232,TEXT(DATE(YEAR(A5),MONTH(A5)+1,1),"mmmm yyyy"),TEXT(DATE(YEAR(A5),MONTH(A5),1),"mmmm yyyy"))) -> September 2026 | L5: =IF(AND(J5="Yes",E5<0),-E5,0) -> 0 | M5: =IF(AND(J5="Yes",E5>0),E5,0) -> 0 | N5: =IF(A5="","",IF(D5="Category Pending","Needs categorization",IF(COUNTIFS($A$2:A5,A5,$B$2:B5,B5,$E$2:E5,E5)>1,"Possible duplicate",""))) -> Needs categorization
A6: 46241 | B6: T-Mobile | C6: TMOBILE PO 12920 SE 38THWA | D6: Mobile Phone | E6: -154.67 | F6: Posted | G6: =IF(A6="","","Checking") -> Checking | H6: Miscellaneous | I6: Uncategorized | J6: =IF(A6="","",IF(OR(H6="Transfers",H6="Income",D6="Transfer",D6="Category Pending"),"No","Yes")) -> Yes | K6: =IF(A6="","",IF(A6>=46232,TEXT(DATE(YEAR(A6),MONTH(A6)+1,1),"mmmm yyyy"),TEXT(DATE(YEAR(A6),MONTH(A6),1),"mmmm yyyy"))) -> September 2026 | L6: =IF(AND(J6="Yes",E6<0),-E6,0) -> 154.67 | M6: =IF(AND(J6="Yes",E6>0),E6,0) -> 0 | N6: =IF(A6="","",IF(D6="Category Pending","Needs categorization",IF(COUNTIFS($A$2:A6,A6,$B$2:B6,B6,$E$2:E6,E6)>1,"Possible duplicate","")))
A7: 46241 | B7: USAA Transfer | C7: USAA FUNDS TRANSFER CR | D7: Transfer | E7: 464 | F7: Posted | G7: =IF(A7="","","Checking") -> Checking | H7: Miscellaneous | I7: Uncategorized | J7: =IF(A7="","",IF(OR(H7="Transfers",H7="Income",D7="Transfer",D7="Category Pending"),"No","Yes")) -> No | K7: =IF(A7="","",IF(A7>=46232,TEXT(DATE(YEAR(A7),MONTH(A7)+1,1),"mmmm yyyy"),TEXT(DATE(YEAR(A7),MONTH(A7),1),"mmmm yyyy"))) -> September 2026 | L7: =IF(AND(J7="Yes",E7<0),-E7,0) -> 0 | M7: =IF(AND(J7="Yes",E7>0),E7,0) -> 0 | N7: =IF(A7="","",IF(D7="Category Pending","Needs categorization",IF(COUNTIFS($A$2:A7,A7,$B$2:B7,B7,$E$2:E7,E7)>1,"Possible duplicate","")))
A8: 46240 | B8: Transfer to Apple Pay | C8: APPLE CASH SENT MONEY 1INFINITELOOPCA | D8: Transfer | E8: -199.51 | F8: Posted | G8: =IF(A8="","","Checking") -> Checking | H8: Miscellaneous | I8: Cash/ATM | J8: =IF(A8="","",IF(OR(H8="Transfers",H8="Income",D8="Transfer",D8="Category Pending"),"No","Yes")) -> No | K8: =IF(A8="","",IF(A8>=46232,TEXT(DATE(YEAR(A8),MONTH(A8)+1,1),"mmmm yyyy"),TEXT(DATE(YEAR(A8),MONTH(A8),1),"mmmm yyyy"))) -> September 2026 | L8: =IF(AND(J8="Yes",E8<0),-E8,0) -> 0 | M8: =IF(AND(J8="Yes",E8>0),E8,0) -> 0 | N8: =IF(A8="","",IF(D8="Category Pending","Needs categorization",IF(COUNTIFS($A$2:A8,A8,$B$2:B8,B8,$E$2:E8,E8)>1,"Possible duplicate","")))
A9: 46239 | B9: Just Energy | C9: JUST ENERGY UTILITIES ***********0431 | D9: Utilities | E9: -362.14 | F9: Posted | G9: =IF(A9="","","Checking") -> Checking | H9: Housing | I9: Home Maintenance | J9: =IF(A9="","",IF(OR(H9="Transfers",H9="Income",D9="Transfer",D9="Category Pending"),"No","Yes")) -> Yes | K9: =IF(A9="","",IF(A9>=46232,TEXT(DATE(YEAR(A9),MONTH(A9)+1,1),"mmmm yyyy"),TEXT(DATE(YEAR(A9),MONTH(A9),1),"mmmm yyyy"))) -> September 2026 | L9: =IF(AND(J9="Yes",E9<0),-E9,0) -> 362.14 | M9: =IF(AND(J9="Yes",E9>0),E9,0) -> 0 | N9: =IF(A9="","",IF(D9="Category Pending","Needs categorization",IF(COUNTIFS($A$2:A9,A9,$B$2:B9,B9,$E$2:E9,E9)>1,"Possible duplicate","")))
A10: 46239 | B10: Just Energy | C10: JUST ENERGY UTILITIES ***********0432 | D10: Utilities | E10: -38.03 | F10: Posted | G10: =IF(A10="","","Checking") -> Checking | H10: Debt | I10: Credit Cards | J10: =IF(A10="","",IF(OR(H10="Transfers",H10="Income",D10="Transfer",D10="Category Pending"),"No","Yes")) -> Yes | K10: =IF(A10="","",IF(A10>=46232,TEXT(DATE(YEAR(A10),MONTH(A10)+1,1),"mmmm yyyy"),TEXT(DATE(YEAR(A10),MONTH(A10),1),"mmmm yyyy"))) -> September 2026 | L10: =IF(AND(J10="Yes",E10<0),-E10,0) -> 38.03 | M10: =IF(AND(J10="Yes",E10>0),E10,0) -> 0 | N10: =IF(A10="","",IF(D10="Category Pending","Needs categorization",IF(COUNTIFS($A$2:A10,A10,$B$2:B10,B10,$E$2:E10,E10)>1,"Possible duplicate","")))
A11: 46239 | B11: H-E-B | C11: H-E-B #721 KILLEEN TX | D11: Groceries | E11: -135.25 | F11: Posted | G11: =IF(A11="","","Checking") -> Checking | H11: Vehicle | I11: Fuel | J11: =IF(A11="","",IF(OR(H11="Transfers",H11="Income",D11="Transfer",D11="Category Pending"),"No","Yes")) -> Yes | K11: =IF(A11="","",IF(A11>=46232,TEXT(DATE(YEAR(A11),MONTH(A11)+1,1),"mmmm yyyy"),TEXT(DATE(YEAR(A11),MONTH(A11),1),"mmmm yyyy"))) -> September 2026 | L11: =IF(AND(J11="Yes",E11<0),-E11,0) -> 135.25 | M11: =IF(AND(J11="Yes",E11>0),E11,0) -> 0 | N11: =IF(A11="","",IF(D11="Category Pending","Needs categorization",IF(COUNTIFS($A$2:A11,A11,$B$2:B11,B11,$E$2:E11,E11)>1,"Possible duplicate","")))
A12: 46239 | B12: Jamaica Nyammingz | C12: JAMAICA NYAMMINGZ KILLEEN TX | D12: Restaurants | E12: -41.59 | F12: Posted | G12: =IF(A12="","","Checking") -> Checking | H12: Miscellaneous | I12: Other | J12: =IF(A12="","",IF(OR(H12="Transfers",H12="Income",D12="Transfer",D12="Category Pending"),"No","Yes")) -> Yes | K12: =IF(A12="","",IF(A12>=46232,TEXT(DATE(YEAR(A12),MONTH(A12)+1,1),"mmmm yyyy"),TEXT(DATE(YEAR(A12),MONTH(A12),1),"mmmm yyyy"))) -> September 2026 | L12: =IF(AND(J12="Yes",E12<0),-E12,0) -> 41.59 | M12: =IF(AND(J12="Yes",E12>0),E12,0) -> 0 | N12: =IF(A12="","",IF(D12="Category Pending","Needs categorization",IF(COUNTIFS($A$2:A12,A12,$B$2:B12,B12,$E$2:E12,E12)>1,"Possible duplicate","")))
A13: 46238 | B13: McDonald's | C13: MCDONALD'S F3011 TEMPLE TX | D13: Fast Food | E13: -14.16 | F13: Posted | G13: =IF(A13="","","Checking") -> Checking | H13: Income | I13: Other Income | J13: =IF(A13="","",IF(OR(H13="Transfers",H13="Income",D13="Transfer",D13="Category Pending"),"No","Yes")) -> No | K13: =IF(A13="","",IF(A13>=46232,TEXT(DATE(YEAR(A13),MONTH(A13)+1,1),"mmmm yyyy"),TEXT(DATE(YEAR(A13),MONTH(A13),1),"mmmm yyyy"))) -> September 2026 | L13: =IF(AND(J13="Yes",E13<0),-E13,0) -> 0 | M13: =IF(AND(J13="Yes",E13>0),E13,0) -> 0 | N13: =IF(A13="","",IF(D13="Category Pending","Needs categorization",IF(COUNTIFS($A$2:A13,A13,$B$2:B13,B13,$E$2:E13,E13)>1,"Possible duplicate","")))
... A42: 46227 | B42: Transfer from Apple Pay | C42: APPLE CASH INST XFER CUPERTINO CA | D42: Transfer | E42: 1278.03 | F42: Posted | G42: =IF(A42="","","Checking") -> Checking | H42: Transfers | I42: Transfers | J42: =IF(A42="","",IF(OR(H42="Transfers",H42="Income",D42="Transfer",D42="Category Pending"),"No","Yes")) -> No | K42: =IF(A42="","",IF(A42>=46232,TEXT(DATE(YEAR(A42),MONTH(A42)+1,1),"mmmm yyyy"),TEXT(DATE(YEAR(A42),MONTH(A42),1),"mmmm yyyy"))) -> July 2026 | L42: =IF(AND(J42="Yes",E42<0),-E42,0) -> 0 | M42: =IF(AND(J42="Yes",E42>0),E42,0) -> 0 | N42: =IF(A42="","",IF(D42="Category Pending","Needs categorization",IF(COUNTIFS($A$2:A42,A42,$B$2:B42,B42,$E$2:E42,E42)>1,"Possible duplicate","")))
G43: =IF(A43="","","Checking") -> Checking | H43: =IF(A43="","",IFERROR(_xlfn.XLOOKUP(D43,Setup!$E$15:$E$79,Setup!$F$15:$F$79),"Miscellaneous")) -> 0 | I43: =IF(A43="","",IFERROR(_xlfn.XLOOKUP(D43,Setup!$E$15:$E$79,Setup!$G$15:$G$79),"Uncategorized")) -> 0 | J43: =IF(A43="","",IF(OR(H43="Transfers",H43="Income",D43="Transfer",D43="Category Pending"),"No","Yes")) -> Yes | K43: =IF(A43="","",IF(A43>=46232,TEXT(DATE(YEAR(A43),MONTH(A43)+1,1),"mmmm yyyy"),TEXT(DATE(YEAR(A43),MONTH(A43),1),"mmmm yyyy"))) -> #VALUE! | L43: =IF(AND(J43="Yes",E43<0),-E43,0) -> 0 | M43: =IF(AND(J43="Yes",E43>0),E43,0) -> 0 | N43: =IF(A43="","",IF(D43="Category Pending","Needs categorization",IF(COUNTIFS($A$2:A43,A43,$B$2:B43,B43,$E$2:E43,E43)>1,"Possible duplicate","")))
G44: =IF(A44="","","Checking") | H44: =IF(A44="","",IFERROR(_xlfn.XLOOKUP(D44,Setup!$E$15:$E$79,Setup!$F$15:$F$79),"Miscellaneous")) | I44: =IF(A44="","",IFERROR(_xlfn.XLOOKUP(D44,Setup!$E$15:$E$79,Setup!$G$15:$G$79),"Uncategorized")) | J44: =IF(A44="","",IF(OR(H44="Transfers",H44="Income",D44="Transfer",D44="Category Pending"),"No","Yes")) | K44: =IF(A44="","",IF(A44>=46232,TEXT(DATE(YEAR(A44),MONTH(A44)+1,1),"mmmm yyyy"),TEXT(DATE(YEAR(A44),MONTH(A44),1),"mmmm yyyy"))) | L44: =IF(AND(J44="Yes",E44<0),-E44,0) -> 0 | M44: =IF(AND(J44="Yes",E44>0),E44,0) -> 0 | N44: =IF(A44="","",IF(D44="Category Pending","Needs categorization",IF(COUNTIFS($A$2:A44,A44,$B$2:B44,B44,$E$2:E44,E44)>1,"Possible duplicate","")))
G45: =IF(A45="","","Checking") | H45: =IF(A45="","",IFERROR(_xlfn.XLOOKUP(D45,Setup!$E$15:$E$79,Setup!$F$15:$F$79),"Miscellaneous")) | I45: =IF(A45="","",IFERROR(_xlfn.XLOOKUP(D45,Setup!$E$15:$E$79,Setup!$G$15:$G$79),"Uncategorized")) | J45: =IF(A45="","",IF(OR(H45="Transfers",H45="Income",D45="Transfer",D45="Category Pending"),"No","Yes")) | K45: =IF(A45="","",IF(A45>=46232,TEXT(DATE(YEAR(A45),MONTH(A45)+1,1),"mmmm yyyy"),TEXT(DATE(YEAR(A45),MONTH(A45),1),"mmmm yyyy"))) | L45: =IF(AND(J45="Yes",E45<0),-E45,0) -> 0 | M45: =IF(AND(J45="Yes",E45>0),E45,0) -> 0 | N45: =IF(A45="","",IF(D45="Category Pending","Needs categorization",IF(COUNTIFS($A$2:A45,A45,$B$2:B45,B45,$E$2:E45,E45)>1,"Possible duplicate","")))
G46: =IF(A46="","","Checking") | H46: =IF(A46="","",IFERROR(_xlfn.XLOOKUP(D46,Setup!$E$15:$E$79,Setup!$F$15:$F$79),"Miscellaneous")) | I46: =IF(A46="","",IFERROR(_xlfn.XLOOKUP(D46,Setup!$E$15:$E$79,Setup!$G$15:$G$79),"Uncategorized")) | J46: =IF(A46="","",IF(OR(H46="Transfers",H46="Income",D46="Transfer",D46="Category Pending"),"No","Yes")) | K46: =IF(A46="","",IF(A46>=46232,TEXT(DATE(YEAR(A46),MONTH(A46)+1,1),"mmmm yyyy"),TEXT(DATE(YEAR(A46),MONTH(A46),1),"mmmm yyyy"))) | L46: =IF(AND(J46="Yes",E46<0),-E46,0) -> 0 | M46: =IF(AND(J46="Yes",E46>0),E46,0) -> 0 | N46: =IF(A46="","",IF(D46="Category Pending","Needs categorization",IF(COUNTIFS($A$2:A46,A46,$B$2:B46,B46,$E$2:E46,E46)>1,"Possible duplicate","")))
G47: =IF(A47="","","Checking") | H47: =IF(A47="","",IFERROR(_xlfn.XLOOKUP(D47,Setup!$E$15:$E$79,Setup!$F$15:$F$79),"Miscellaneous")) | I47: =IF(A47="","",IFERROR(_xlfn.XLOOKUP(D47,Setup!$E$15:$E$79,Setup!$G$15:$G$79),"Uncategorized")) | J47: =IF(A47="","",IF(OR(H47="Transfers",H47="Income",D47="Transfer",D47="Category Pending"),"No","Yes")) | K47: =IF(A47="","",IF(A47>=46232,TEXT(DATE(YEAR(A47),MONTH(A47)+1,1),"mmmm yyyy"),TEXT(DATE(YEAR(A47),MONTH(A47),1),"mmmm yyyy"))) | L47: =IF(AND(J47="Yes",E47<0),-E47,0) -> 0 | M47: =IF(AND(J47="Yes",E47>0),E47,0) -> 0 | N47: =IF(A47="","",IF(D47="Category Pending","Needs categorization",IF(COUNTIFS($A$2:A47,A47,$B$2:B47,B47,$E$2:E47,E47)>1,"Possible duplicate","")))
G48: =IF(A48="","","Checking") | H48: =IF(A48="","",IFERROR(_xlfn.XLOOKUP(D48,Setup!$E$15:$E$79,Setup!$F$15:$F$79),"Miscellaneous")) | I48: =IF(A48="","",IFERROR(_xlfn.XLOOKUP(D48,Setup!$E$15:$E$79,Setup!$G$15:$G$79),"Uncategorized")) | J48: =IF(A48="","",IF(OR(H48="Transfers",H48="Income",D48="Transfer",D48="Category Pending"),"No","Yes")) | K48: =IF(A48="","",IF(A48>=46232,TEXT(DATE(YEAR(A48),MONTH(A48)+1,1),"mmmm yyyy"),TEXT(DATE(YEAR(A48),MONTH(A48),1),"mmmm yyyy"))) | L48: =IF(AND(J48="Yes",E48<0),-E48,0) -> 0 | M48: =IF(AND(J48="Yes",E48>0),E48,0) -> 0 | N48: =IF(A48="","",IF(D48="Category Pending","Needs categorization",IF(COUNTIFS($A$2:A48,A48,$B$2:B48,B48,$E$2:E48,E48)>1,"Possible duplicate","")))
G49: =IF(A49="","","Checking") | H49: =IF(A49="","",IFERROR(_xlfn.XLOOKUP(D49,Setup!$E$15:$E$79,Setup!$F$15:$F$79),"Miscellaneous")) | I49: =IF(A49="","",IFERROR(_xlfn.XLOOKUP(D49,Setup!$E$15:$E$79,Setup!$G$15:$G$79),"Uncategorized")) | J49: =IF(A49="","",IF(OR(H49="Transfers",H49="Income",D49="Transfer",D49="Category Pending"),"No","Yes")) | K49: =IF(A49="","",IF(A49>=46232,TEXT(DATE(YEAR(A49),MONTH(A49)+1,1),"mmmm yyyy"),TEXT(DATE(YEAR(A49),MONTH(A49),1),"mmmm yyyy"))) | L49: =IF(AND(J49="Yes",E49<0),-E49,0) -> 0 | M49: =IF(AND(J49="Yes",E49>0),E49,0) -> 0 | N49: =IF(A49="","",IF(D49="Category Pending","Needs categorization",IF(COUNTIFS($A$2:A49,A49,$B$2:B49,B49,$E$2:E49,E49)>1,"Possible duplicate","")))
G50: =IF(A50="","","Checking") | H50: =IF(A50="","",IFERROR(_xlfn.XLOOKUP(D50,Setup!$E$15:$E$79,Setup!$F$15:$F$79),"Miscellaneous")) | I50: =IF(A50="","",IFERROR(_xlfn.XLOOKUP(D50,Setup!$E$15:$E$79,Setup!$G$15:$G$79),"Uncategorized")) | J50: =IF(A50="","",IF(OR(H50="Transfers",H50="Income",D50="Transfer",D50="Category Pending"),"No","Yes")) | K50: =IF(A50="","",IF(A50>=46232,TEXT(DATE(YEAR(A50),MONTH(A50)+1,1),"mmmm yyyy"),TEXT(DATE(YEAR(A50),MONTH(A50),1),"mmmm yyyy"))) | L50: =IF(AND(J50="Yes",E50<0),-E50,0) -> 0 | M50: =IF(AND(J50="Yes",E50>0),E50,0) -> 0 | N50: =IF(A50="","",IF(D50="Category Pending","Needs categorization",IF(COUNTIFS($A$2:A50,A50,$B$2:B50,B50,$E$2:E50,E50)>1,"Possible duplicate","")))
G51: =IF(A51="","","Checking") | H51: =IF(A51="","",IFERROR(_xlfn.XLOOKUP(D51,Setup!$E$15:$E$79,Setup!$F$15:$F$79),"Miscellaneous")) | I51: =IF(A51="","",IFERROR(_xlfn.XLOOKUP(D51,Setup!$E$15:$E$79,Setup!$G$15:$G$79),"Uncategorized")) | J51: =IF(A51="","",IF(OR(H51="Transfers",H51="Income",D51="Transfer",D51="Category Pending"),"No","Yes")) | K51: =IF(A51="","",IF(A51>=46232,TEXT(DATE(YEAR(A51),MONTH(A51)+1,1),"mmmm yyyy"),TEXT(DATE(YEAR(A51),MONTH(A51),1),"mmmm yyyy"))) | L51: =IF(AND(J51="Yes",E51<0),-E51,0) -> 0 | M51: =IF(AND(J51="Yes",E51>0),E51,0) -> 0 | N51: =IF(A51="","",IF(D51="Category Pending","Needs categorization",IF(COUNTIFS($A$2:A51,A51,$B$2:B51,B51,$E$2:E51,E51)>1,"Possible duplicate","")))
G52: =IF(A52="","","Checking") | H52: =IF(A52="","",IFERROR(_xlfn.XLOOKUP(D52,Setup!$E$15:$E$79,Setup!$F$15:$F$79),"Miscellaneous")) | I52: =IF(A52="","",IFERROR(_xlfn.XLOOKUP(D52,Setup!$E$15:$E$79,Setup!$G$15:$G$79),"Uncategorized")) | J52: =IF(A52="","",IF(OR(H52="Transfers",H52="Income",D52="Transfer",D52="Category Pending"),"No","Yes")) | K52: =IF(A52="","",IF(A52>=46232,TEXT(DATE(YEAR(A52),MONTH(A52)+1,1),"mmmm yyyy"),TEXT(DATE(YEAR(A52),MONTH(A52),1),"mmmm yyyy"))) | L52: =IF(AND(J52="Yes",E52<0),-E52,0) -> 0 | M52: =IF(AND(J52="Yes",E52>0),E52,0) -> 0 | N52: =IF(A52="","",IF(D52="Category Pending","Needs categorization",IF(COUNTIFS($A$2:A52,A52,$B$2:B52,B52,$E$2:E52,E52)>1,"Possible duplicate","")))
G53: =IF(A53="","","Checking") | H53: =IF(A53="","",IFERROR(_xlfn.XLOOKUP(D53,Setup!$E$15:$E$79,Setup!$F$15:$F$79),"Miscellaneous")) | I53: =IF(A53="","",IFERROR(_xlfn.XLOOKUP(D53,Setup!$E$15:$E$79,Setup!$G$15:$G$79),"Uncategorized")) | J53: =IF(A53="","",IF(OR(H53="Transfers",H53="Income",D53="Transfer",D53="Category Pending"),"No","Yes")) | K53: =IF(A53="","",IF(A53>=46232,TEXT(DATE(YEAR(A53),MONTH(A53)+1,1),"mmmm yyyy"),TEXT(DATE(YEAR(A53),MONTH(A53),1),"mmmm yyyy"))) | L53: =IF(AND(J53="Yes",E53<0),-E53,0) -> 0 | M53: =IF(AND(J53="Yes",E53>0),E53,0) -> 0 | N53: =IF(A53="","",IF(D53="Category Pending","Needs categorization",IF(COUNTIFS($A$2:A53,A53,$B$2:B53,B53,$E$2:E53,E53)>1,"Possible duplicate","")))
G54: =IF(A54="","","Checking") | H54: =IF(A54="","",IFERROR(_xlfn.XLOOKUP(D54,Setup!$E$15:$E$79,Setup!$F$15:$F$79),"Miscellaneous")) | I54: =IF(A54="","",IFERROR(_xlfn.XLOOKUP(D54,Setup!$E$15:$E$79,Setup!$G$15:$G$79),"Uncategorized")) | J54: =IF(A54="","",IF(OR(H54="Transfers",H54="Income",D54="Transfer",D54="Category Pending"),"No","Yes")) | K54: =IF(A54="","",IF(A54>=46232,TEXT(DATE(YEAR(A54),MONTH(A54)+1,1),"mmmm yyyy"),TEXT(DATE(YEAR(A54),MONTH(A54),1),"mmmm yyyy"))) | L54: =IF(AND(J54="Yes",E54<0),-E54,0) -> 0 | M54: =IF(AND(J54="Yes",E54>0),E54,0) -> 0 | N54: =IF(A54="","",IF(D54="Category Pending","Needs categorization",IF(COUNTIFS($A$2:A54,A54,$B$2:B54,B54,$E$2:E54,E54)>1,"Possible duplicate","")))
... G1902: =IF(A1902="","","Checking") | H1902: =IF(A1902="","",IFERROR(_xlfn.XLOOKUP(D1902,Setup!$E$15:$E$79,Setup!$F$15:$F$79),"Miscellaneous")) | I1902: =IF(A1902="","",IFERROR(_xlfn.XLOOKUP(D1902,Setup!$E$15:$E$79,Setup!$G$15:$G$79),"Uncategorized")) | J1902: =IF(A1902="","",IF(OR(H1902="Transfers",H1902="Income",D1902="Transfer",D1902="Category Pending"),"No","Yes")) | K1902: =IF(A1902="","",IF(A1902>=46232,TEXT(DATE(YEAR(A1902),MONTH(A1902)+1,1),"mmmm yyyy"),TEXT(DATE(YEAR(A1902),MONTH(A1902),1),"mmmm yyyy"))) | L1902: =IF(AND(J1902="Yes",E1902<0),-E1902,0) -> 0 | M1902: =IF(AND(J1902="Yes",E1902>0),E1902,0) -> 0 | N1902: =IF(A1902="","",IF(D1902="Category Pending","Needs categorization",IF(COUNTIFS($A$2:A1902,A1902,$B$2:B1902,B1902,$E$2:E1902,E1902)>1,"Possible duplicate","")))
